Aeolus/src/ALU.v
// Arithmetic Logic Unit

// Arithmetic Unit Components
/*
         Arithmetic Unit
              \
            8-bit RC Adder
                 \
                4-Bit Adder
                    \     
                Full adder 
*/


module ArithmeticUnit (
    input wire       clk,
    input wire       reset,
    input            add,
    input            sub,
    input            lshift,
    input            rshift,
    input wire [3:0] in1,
    input wire [3:0] in2, 
    output reg [3:0] out,
    output reg       overflow

);

    wire [3:0] shiftOut, adderOut, subtractorOut;
    wire shiftFlag, adderOverflowFlag, subtractorOverflowFlag;

    ShiftRegister       sr         (in1, {lshift,rshift}, shiftOut, shiftFlag);
    CombAdder_4bit      adder      (in1, in2, adderOut, adderOverflowFlag);
    CombSubtractor_4bit subtractor (in1, in2, subtractorOut, subtractorOverflowFlag);

    always @(posedge clk) begin // assumes control signals can't be sent together
        
        if (add) begin
            out <= adderOut;
            overflow <= adderOverflowFlag;
        end

        if (sub) begin
            out <= subtractorOut;
            overflow <= subtractorOverflowFlag;
        end

        if (lshift || rshift)
            out <= shiftOut;
            overflow <= shiftFlag;
    end



endmodule


module ShiftRegister( // combinational shift register
        input wire [3:0] in,
        input      [1:0] shiftstate,  //reg
        output reg [3:0] out,
        output reg       flag
);

    always @(*) begin
        if (shiftstate == 2'b10) begin // LSH
             {flag,out} = in << 1;
        end if (shiftstate == 2'b01) begin // RSH
            {flag,out} = in >> 1;
        end
    end

endmodule

module FullAdder(
    input wire in1,
    input wire in2,
    input wire carryIn,
    output  sum,
    output  carryOut
);
    assign {carryOut,sum} = in1 + in2; // behavioural description

endmodule

// ripple carry adder 4-bits - not verified
module SyncRippleCarryAdder_4bit ( // synchronous design, hierarchal desgin
    input wire         clk,
    input wire         reset,
    input wire  [3:0]  in1,
    input wire  [3:0]  in2,
    output reg  [3:0]  out,
    output reg         overflow
);
    wire carry1,carry2,carry3,carry4;
    reg c1, c2, c3;

    wire o0, o1, o2, o3;

    FullAdder f1 (in1[0], in2[0], 1'b0, o0, carry1);
    FullAdder f2 (in1[1], in2[1], c1,   o1, carry2);
    FullAdder f3 (in1[2], in2[2], c2,   o2, carry3);
    FullAdder f4 (in1[3], in2[3], c3,   o3, carry4);

    always @(posedge clk) begin
        if (~reset) begin
            c1 <= carry1;
            c2 <= carry2;
            c3 <= carry3;

            out[0] <= o0;
            out[1] <= o1;
            out[2] <= o2;
            out[3] <= o3;
            overflow <= carry4;
        
        end else begin
            c1 <= 0;
            c2 <= 0;
            c3 <= 0;

            out[0] <= 0;
            out[1] <= 0;
            out[2] <= 0;
            out[3] <= 0;
            overflow <= 0;
        end

    end

endmodule

// 4-bit adder
module CombAdder_4bit ( // Conbinational, Behavioural Description
    input wire  [3:0]  in1,
    input wire  [3:0]  in2,
    output reg  [3:0]  out,
    output reg         overflow  
);

    always @(*) begin
        {overflow, out} <= in1 + in2;
    end

endmodule

//  4-bit Subtractor
module CombSubtractor_4bit (  // Combinational - Behavioural Description
    input wire  [3:0]  in1,
    input wire  [3:0]  in2,
    output reg  [3:0]  out,
    output reg         overflow  
);

    always @(*) begin
        {overflow, out} <= in1 - in2;
    end

endmodule

// 4-bit Adder
module SyncAdder_4bit (  // Synchronous, Behavioural Descriptiion
    input wire         clk,
    input wire         reset,
    input wire  [3:0]  in1,
    input wire  [3:0]  in2,
    output reg  [3:0]  out,
    output reg         overflow  // what does this represent in a subtractionn?
);
    always @(posedge clk) begin
        if (~reset) begin
            {overflow, out} <= in1 + in2;
        end begin
            out <= 0;
        end
    end 

endmodule

//4-bit Subtractor
module SyncSubtractor_4bit (  // Synchronous, Behavioural Descriptiion
    input wire         clk,
    input wire         reset,
    input wire  [3:0]  in1,
    input wire  [3:0]  in2,
    output reg  [3:0]  out,
    output reg         overflow  // what does this represent in a subtractionn?
);

    always @(posedge clk ) begin
        if (~reset) begin
            {overflow, out} <= in1 - in2;
        end begin
            out <= 0;
        end
    end 

endmodule

Aeolus/test/adderTB.v

//Adder Testbench
`include "src/ALU.v"

`define assert(signal, value) if (signal !== value) begin  $display("ASSERTION FAILED in %m: signal != value -> %d != %d", signal, value); $finish; end

module AdderTb();

    reg        CLK;
    reg        RESET;
    reg  [3:0] IN1, IN2;
    wire [3:0] OUT;
    wire       OVERFLOW;
    
    integer i;

    CombAdder_4bit uut (IN1, IN2, OUT, OVERFLOW);

    initial begin

        $dumpfile("src/test/vcd/adderdump.vcd");
        $dumpvars(0, AdderTb);
        
        IN1 = 0; IN2 = 0; 

        $display("4-Bit Adder Test");
       //$display("   in1   |  in2     |  actual    |  expected");

        for (i = 0; i < 256 ; i = i + 1) begin
            #10 {IN2,IN1} = i[7:0];
            //#5  $display("  %4b    |   %4b  |   %4b   |   %5b   " ,IN1, IN2,  (i[3:0] + i[7:4]) , {OVERFLOW,OUT} );
            #5  `assert({OVERFLOW,OUT}, (i[3:0] + i[7:4]));  // assert that the result is the addition
        end

        $display("TEST SUCCESSFUL!"); $finish; 
    end

endmodule

Aeolus/adderdump.vcd
$date
	Tue Feb 18 10:46:03 2025
$end
$version
	Icarus Verilog
$end
$timescale
	1s
$end
$scope module AdderTb $end
$var wire 1 ! OVERFLOW $end
$var wire 4 " OUT [3:0] $end
$var reg 4 # IN1 [3:0] $end
$var reg 4 $ IN2 [3:0] $end
$var integer 32 % i [31:0] $end
$scope module uut $end
$var wire 4 & in1 [3:0] $end
$var wire 4 ' in2 [3:0] $end
$var reg 4 ( out [3:0] $end
$var reg 1 ! overflow $end
$upscope $end
$upscope $end
$enddefinitions $end
$comment Show the parameter values. $end
$dumpall
$end
#0
$dumpvars
b0 (
b0 '
b0 &
b0 %
b0 $
b0 #
b0 "
0!
$end
#15
b1 %
#25
b1 "
b1 (
b1 #
b1 &
#30
b10 %
#40
b10 "
b10 (
b10 #
b10 &
#45
b11 %
#55
b11 "
b11 (
b11 #
b11 &
#60
b100 %
#70
b100 "
b100 (
b100 #
b100 &
#75
b101 %
#85
b101 "
b101 (
b101 #
b101 &
#90
b110 %
#100
b110 "
b110 (
b110 #
b110 &
#105
b111 %
#115
b111 "
b111 (
b111 #
b111 &
#120
b1000 %
#130
b1000 "
b1000 (
b1000 #
b1000 &
#135
b1001 %
#145
b1001 "
b1001 (
b1001 #
b1001 &
#150
b1010 %
#160
b1010 "
b1010 (
b1010 #
b1010 &
#165
b1011 %
#175
b1011 "
b1011 (
b1011 #
b1011 &
#180
b1100 %
#190
b1100 "
b1100 (
b1100 #
b1100 &
#195
b1101 %
#205
b1101 "
b1101 (
b1101 #
b1101 &
#210
b1110 %
#220
b1110 "
b1110 (
b1110 #
b1110 &
#225
b1111 %
#235
b1111 "
b1111 (
b1111 #
b1111 &
#240
b10000 %
#250
b1 "
b1 (
b1 $
b1 '
b0 #
b0 &
#255
b10001 %
#265
b10 "
b10 (
b1 #
b1 &
#270
b10010 %
#280
b11 "
b11 (
b10 #
b10 &
#285
b10011 %
#295
b100 "
b100 (
b11 #
b11 &
#300
b10100 %
#310
b101 "
b101 (
b100 #
b100 &
#315
b10101 %
#325
b110 "
b110 (
b101 #
b101 &
#330
b10110 %
#340
b111 "
b111 (
b110 #
b110 &
#345
b10111 %
#355
b1000 "
b1000 (
b111 #
b111 &
#360
b11000 %
#370
b1001 "
b1001 (
b1000 #
b1000 &
#375
b11001 %
#385
b1010 "
b1010 (
b1001 #
b1001 &
#390
b11010 %
#400
b1011 "
b1011 (
b1010 #
b1010 &
#405
b11011 %
#415
b1100 "
b1100 (
b1011 #
b1011 &
#420
b11100 %
#430
b1101 "
b1101 (
b1100 #
b1100 &
#435
b11101 %
#445
b1110 "
b1110 (
b1101 #
b1101 &
#450
b11110 %
#460
b1111 "
b1111 (
b1110 #
b1110 &
#465
b11111 %
#475
1!
b0 "
b0 (
b1111 #
b1111 &
#480
b100000 %
#490
0!
b10 "
b10 (
b10 $
b10 '
b0 #
b0 &
#495
b100001 %
#505
b11 "
b11 (
b1 #
b1 &
#510
b100010 %
#520
b100 "
b100 (
b10 #
b10 &
#525
b100011 %
#535
b101 "
b101 (
b11 #
b11 &
#540
b100100 %
#550
b110 "
b110 (
b100 #
b100 &
#555
b100101 %
#565
b111 "
b111 (
b101 #
b101 &
#570
b100110 %
#580
b1000 "
b1000 (
b110 #
b110 &
#585
b100111 %
#595
b1001 "
b1001 (
b111 #
b111 &
#600
b101000 %
#610
b1010 "
b1010 (
b1000 #
b1000 &
#615
b101001 %
#625
b1011 "
b1011 (
b1001 #
b1001 &
#630
b101010 %
#640
b1100 "
b1100 (
b1010 #
b1010 &
#645
b101011 %
#655
b1101 "
b1101 (
b1011 #
b1011 &
#660
b101100 %
#670
b1110 "
b1110 (
b1100 #
b1100 &
#675
b101101 %
#685
b1111 "
b1111 (
b1101 #
b1101 &
#690
b101110 %
#700
1!
b0 "
b0 (
b1110 #
b1110 &
#705
b101111 %
#715
b1 "
b1 (
b1111 #
b1111 &
#720
b110000 %
#730
0!
b11 "
b11 (
b11 $
b11 '
b0 #
b0 &
#735
b110001 %
#745
b100 "
b100 (
b1 #
b1 &
#750
b110010 %
#760
b101 "
b101 (
b10 #
b10 &
#765
b110011 %
#775
b110 "
b110 (
b11 #
b11 &
#780
b110100 %
#790
b111 "
b111 (
b100 #
b100 &
#795
b110101 %
#805
b1000 "
b1000 (
b101 #
b101 &
#810
b110110 %
#820
b1001 "
b1001 (
b110 #
b110 &
#825
b110111 %
#835
b1010 "
b1010 (
b111 #
b111 &
#840
b111000 %
#850
b1011 "
b1011 (
b1000 #
b1000 &
#855
b111001 %
#865
b1100 "
b1100 (
b1001 #
b1001 &
#870
b111010 %
#880
b1101 "
b1101 (
b1010 #
b1010 &
#885
b111011 %
#895
b1110 "
b1110 (
b1011 #
b1011 &
#900
b111100 %
#910
b1111 "
b1111 (
b1100 #
b1100 &
#915
b111101 %
#925
1!
b0 "
b0 (
b1101 #
b1101 &
#930
b111110 %
#940
b1 "
b1 (
b1110 #
b1110 &
#945
b111111 %
#955
b10 "
b10 (
b1111 #
b1111 &
#960
b1000000 %
#970
0!
b100 "
b100 (
b100 $
b100 '
b0 #
b0 &
#975
b1000001 %
#985
b101 "
b101 (
b1 #
b1 &
#990
b1000010 %
#1000
b110 "
b110 (
b10 #
b10 &
#1005
b1000011 %
#1015
b111 "
b111 (
b11 #
b11 &
#1020
b1000100 %
#1030
b1000 "
b1000 (
b100 #
b100 &
#1035
b1000101 %
#1045
b1001 "
b1001 (
b101 #
b101 &
#1050
b1000110 %
#1060
b1010 "
b1010 (
b110 #
b110 &
#1065
b1000111 %
#1075
b1011 "
b1011 (
b111 #
b111 &
#1080
b1001000 %
#1090
b1100 "
b1100 (
b1000 #
b1000 &
#1095
b1001001 %
#1105
b1101 "
b1101 (
b1001 #
b1001 &
#1110
b1001010 %
#1120
b1110 "
b1110 (
b1010 #
b1010 &
#1125
b1001011 %
#1135
b1111 "
b1111 (
b1011 #
b1011 &
#1140
b1001100 %
#1150
1!
b0 "
b0 (
b1100 #
b1100 &
#1155
b1001101 %
#1165
b1 "
b1 (
b1101 #
b1101 &
#1170
b1001110 %
#1180
b10 "
b10 (
b1110 #
b1110 &
#1185
b1001111 %
#1195
b11 "
b11 (
b1111 #
b1111 &
#1200
b1010000 %
#1210
0!
b101 "
b101 (
b101 $
b101 '
b0 #
b0 &
#1215
b1010001 %
#1225
b110 "
b110 (
b1 #
b1 &
#1230
b1010010 %
#1240
b111 "
b111 (
b10 #
b10 &
#1245
b1010011 %
#1255
b1000 "
b1000 (
b11 #
b11 &
#1260
b1010100 %
#1270
b1001 "
b1001 (
b100 #
b100 &
#1275
b1010101 %
#1285
b1010 "
b1010 (
b101 #
b101 &
#1290
b1010110 %
#1300
b1011 "
b1011 (
b110 #
b110 &
#1305
b1010111 %
#1315
b1100 "
b1100 (
b111 #
b111 &
#1320
b1011000 %
#1330
b1101 "
b1101 (
b1000 #
b1000 &
#1335
b1011001 %
#1345
b1110 "
b1110 (
b1001 #
b1001 &
#1350
b1011010 %
#1360
b1111 "
b1111 (
b1010 #
b1010 &
#1365
b1011011 %
#1375
1!
b0 "
b0 (
b1011 #
b1011 &
#1380
b1011100 %
#1390
b1 "
b1 (
b1100 #
b1100 &
#1395
b1011101 %
#1405
b10 "
b10 (
b1101 #
b1101 &
#1410
b1011110 %
#1420
b11 "
b11 (
b1110 #
b1110 &
#1425
b1011111 %
#1435
b100 "
b100 (
b1111 #
b1111 &
#1440
b1100000 %
#1450
0!
b110 "
b110 (
b110 $
b110 '
b0 #
b0 &
#1455
b1100001 %
#1465
b111 "
b111 (
b1 #
b1 &
#1470
b1100010 %
#1480
b1000 "
b1000 (
b10 #
b10 &
#1485
b1100011 %
#1495
b1001 "
b1001 (
b11 #
b11 &
#1500
b1100100 %
#1510
b1010 "
b1010 (
b100 #
b100 &
#1515
b1100101 %
#1525
b1011 "
b1011 (
b101 #
b101 &
#1530
b1100110 %
#1540
b1100 "
b1100 (
b110 #
b110 &
#1545
b1100111 %
#1555
b1101 "
b1101 (
b111 #
b111 &
#1560
b1101000 %
#1570
b1110 "
b1110 (
b1000 #
b1000 &
#1575
b1101001 %
#1585
b1111 "
b1111 (
b1001 #
b1001 &
#1590
b1101010 %
#1600
1!
b0 "
b0 (
b1010 #
b1010 &
#1605
b1101011 %
#1615
b1 "
b1 (
b1011 #
b1011 &
#1620
b1101100 %
#1630
b10 "
b10 (
b1100 #
b1100 &
#1635
b1101101 %
#1645
b11 "
b11 (
b1101 #
b1101 &
#1650
b1101110 %
#1660
b100 "
b100 (
b1110 #
b1110 &
#1665
b1101111 %
#1675
b101 "
b101 (
b1111 #
b1111 &
#1680
b1110000 %
#1690
0!
b111 "
b111 (
b111 $
b111 '
b0 #
b0 &
#1695
b1110001 %
#1705
b1000 "
b1000 (
b1 #
b1 &
#1710
b1110010 %
#1720
b1001 "
b1001 (
b10 #
b10 &
#1725
b1110011 %
#1735
b1010 "
b1010 (
b11 #
b11 &
#1740
b1110100 %
#1750
b1011 "
b1011 (
b100 #
b100 &
#1755
b1110101 %
#1765
b1100 "
b1100 (
b101 #
b101 &
#1770
b1110110 %
#1780
b1101 "
b1101 (
b110 #
b110 &
#1785
b1110111 %
#1795
b1110 "
b1110 (
b111 #
b111 &
#1800
b1111000 %
#1810
b1111 "
b1111 (
b1000 #
b1000 &
#1815
b1111001 %
#1825
1!
b0 "
b0 (
b1001 #
b1001 &
#1830
b1111010 %
#1840
b1 "
b1 (
b1010 #
b1010 &
#1845
b1111011 %
#1855
b10 "
b10 (
b1011 #
b1011 &
#1860
b1111100 %
#1870
b11 "
b11 (
b1100 #
b1100 &
#1875
b1111101 %
#1885
b100 "
b100 (
b1101 #
b1101 &
#1890
b1111110 %
#1900
b101 "
b101 (
b1110 #
b1110 &
#1905
b1111111 %
#1915
b110 "
b110 (
b1111 #
b1111 &
#1920
b10000000 %
#1930
0!
b1000 "
b1000 (
b1000 $
b1000 '
b0 #
b0 &
#1935
b10000001 %
#1945
b1001 "
b1001 (
b1 #
b1 &
#1950
b10000010 %
#1960
b1010 "
b1010 (
b10 #
b10 &
#1965
b10000011 %
#1975
b1011 "
b1011 (
b11 #
b11 &
#1980
b10000100 %
#1990
b1100 "
b1100 (
b100 #
b100 &
#1995
b10000101 %
#2005
b1101 "
b1101 (
b101 #
b101 &
#2010
b10000110 %
#2020
b1110 "
b1110 (
b110 #
b110 &
#2025
b10000111 %
#2035
b1111 "
b1111 (
b111 #
b111 &
#2040
b10001000 %
#2050
1!
b0 "
b0 (
b1000 #
b1000 &
#2055
b10001001 %
#2065
b1 "
b1 (
b1001 #
b1001 &
#2070
b10001010 %
#2080
b10 "
b10 (
b1010 #
b1010 &
#2085
b10001011 %
#2095
b11 "
b11 (
b1011 #
b1011 &
#2100
b10001100 %
#2110
b100 "
b100 (
b1100 #
b1100 &
#2115
b10001101 %
#2125
b101 "
b101 (
b1101 #
b1101 &
#2130
b10001110 %
#2140
b110 "
b110 (
b1110 #
b1110 &
#2145
b10001111 %
#2155
b111 "
b111 (
b1111 #
b1111 &
#2160
b10010000 %
#2170
0!
b1001 "
b1001 (
b1001 $
b1001 '
b0 #
b0 &
#2175
b10010001 %
#2185
b1010 "
b1010 (
b1 #
b1 &
#2190
b10010010 %
#2200
b1011 "
b1011 (
b10 #
b10 &
#2205
b10010011 %
#2215
b1100 "
b1100 (
b11 #
b11 &
#2220
b10010100 %
#2230
b1101 "
b1101 (
b100 #
b100 &
#2235
b10010101 %
#2245
b1110 "
b1110 (
b101 #
b101 &
#2250
b10010110 %
#2260
b1111 "
b1111 (
b110 #
b110 &
#2265
b10010111 %
#2275
1!
b0 "
b0 (
b111 #
b111 &
#2280
b10011000 %
#2290
b1 "
b1 (
b1000 #
b1000 &
#2295
b10011001 %
#2305
b10 "
b10 (
b1001 #
b1001 &
#2310
b10011010 %
#2320
b11 "
b11 (
b1010 #
b1010 &
#2325
b10011011 %
#2335
b100 "
b100 (
b1011 #
b1011 &
#2340
b10011100 %
#2350
b101 "
b101 (
b1100 #
b1100 &
#2355
b10011101 %
#2365
b110 "
b110 (
b1101 #
b1101 &
#2370
b10011110 %
#2380
b111 "
b111 (
b1110 #
b1110 &
#2385
b10011111 %
#2395
b1000 "
b1000 (
b1111 #
b1111 &
#2400
b10100000 %
#2410
0!
b1010 "
b1010 (
b1010 $
b1010 '
b0 #
b0 &
#2415
b10100001 %
#2425
b1011 "
b1011 (
b1 #
b1 &
#2430
b10100010 %
#2440
b1100 "
b1100 (
b10 #
b10 &
#2445
b10100011 %
#2455
b1101 "
b1101 (
b11 #
b11 &
#2460
b10100100 %
#2470
b1110 "
b1110 (
b100 #
b100 &
#2475
b10100101 %
#2485
b1111 "
b1111 (
b101 #
b101 &
#2490
b10100110 %
#2500
1!
b0 "
b0 (
b110 #
b110 &
#2505
b10100111 %
#2515
b1 "
b1 (
b111 #
b111 &
#2520
b10101000 %
#2530
b10 "
b10 (
b1000 #
b1000 &
#2535
b10101001 %
#2545
b11 "
b11 (
b1001 #
b1001 &
#2550
b10101010 %
#2560
b100 "
b100 (
b1010 #
b1010 &
#2565
b10101011 %
#2575
b101 "
b101 (
b1011 #
b1011 &
#2580
b10101100 %
#2590
b110 "
b110 (
b1100 #
b1100 &
#2595
b10101101 %
#2605
b111 "
b111 (
b1101 #
b1101 &
#2610
b10101110 %
#2620
b1000 "
b1000 (
b1110 #
b1110 &
#2625
b10101111 %
#2635
b1001 "
b1001 (
b1111 #
b1111 &
#2640
b10110000 %
#2650
0!
b1011 "
b1011 (
b1011 $
b1011 '
b0 #
b0 &
#2655
b10110001 %
#2665
b1100 "
b1100 (
b1 #
b1 &
#2670
b10110010 %
#2680
b1101 "
b1101 (
b10 #
b10 &
#2685
b10110011 %
#2695
b1110 "
b1110 (
b11 #
b11 &
#2700
b10110100 %
#2710
b1111 "
b1111 (
b100 #
b100 &
#2715
b10110101 %
#2725
1!
b0 "
b0 (
b101 #
b101 &
#2730
b10110110 %
#2740
b1 "
b1 (
b110 #
b110 &
#2745
b10110111 %
#2755
b10 "
b10 (
b111 #
b111 &
#2760
b10111000 %
#2770
b11 "
b11 (
b1000 #
b1000 &
#2775
b10111001 %
#2785
b100 "
b100 (
b1001 #
b1001 &
#2790
b10111010 %
#2800
b101 "
b101 (
b1010 #
b1010 &
#2805
b10111011 %
#2815
b110 "
b110 (
b1011 #
b1011 &
#2820
b10111100 %
#2830
b111 "
b111 (
b1100 #
b1100 &
#2835
b10111101 %
#2845
b1000 "
b1000 (
b1101 #
b1101 &
#2850
b10111110 %
#2860
b1001 "
b1001 (
b1110 #
b1110 &
#2865
b10111111 %
#2875
b1010 "
b1010 (
b1111 #
b1111 &
#2880
b11000000 %
#2890
0!
b1100 "
b1100 (
b1100 $
b1100 '
b0 #
b0 &
#2895
b11000001 %
#2905
b1101 "
b1101 (
b1 #
b1 &
#2910
b11000010 %
#2920
b1110 "
b1110 (
b10 #
b10 &
#2925
b11000011 %
#2935
b1111 "
b1111 (
b11 #
b11 &
#2940
b11000100 %
#2950
1!
b0 "
b0 (
b100 #
b100 &
#2955
b11000101 %
#2965
b1 "
b1 (
b101 #
b101 &
#2970
b11000110 %
#2980
b10 "
b10 (
b110 #
b110 &
#2985
b11000111 %
#2995
b11 "
b11 (
b111 #
b111 &
#3000
b11001000 %
#3010
b100 "
b100 (
b1000 #
b1000 &
#3015
b11001001 %
#3025
b101 "
b101 (
b1001 #
b1001 &
#3030
b11001010 %
#3040
b110 "
b110 (
b1010 #
b1010 &
#3045
b11001011 %
#3055
b111 "
b111 (
b1011 #
b1011 &
#3060
b11001100 %
#3070
b1000 "
b1000 (
b1100 #
b1100 &
#3075
b11001101 %
#3085
b1001 "
b1001 (
b1101 #
b1101 &
#3090
b11001110 %
#3100
b1010 "
b1010 (
b1110 #
b1110 &
#3105
b11001111 %
#3115
b1011 "
b1011 (
b1111 #
b1111 &
#3120
b11010000 %
#3130
0!
b1101 "
b1101 (
b1101 $
b1101 '
b0 #
b0 &
#3135
b11010001 %
#3145
b1110 "
b1110 (
b1 #
b1 &
#3150
b11010010 %
#3160
b1111 "
b1111 (
b10 #
b10 &
#3165
b11010011 %
#3175
1!
b0 "
b0 (
b11 #
b11 &
#3180
b11010100 %
#3190
b1 "
b1 (
b100 #
b100 &
#3195
b11010101 %
#3205
b10 "
b10 (
b101 #
b101 &
#3210
b11010110 %
#3220
b11 "
b11 (
b110 #
b110 &
#3225
b11010111 %
#3235
b100 "
b100 (
b111 #
b111 &
#3240
b11011000 %
#3250
b101 "
b101 (
b1000 #
b1000 &
#3255
b11011001 %
#3265
b110 "
b110 (
b1001 #
b1001 &
#3270
b11011010 %
#3280
b111 "
b111 (
b1010 #
b1010 &
#3285
b11011011 %
#3295
b1000 "
b1000 (
b1011 #
b1011 &
#3300
b11011100 %
#3310
b1001 "
b1001 (
b1100 #
b1100 &
#3315
b11011101 %
#3325
b1010 "
b1010 (
b1101 #
b1101 &
#3330
b11011110 %
#3340
b1011 "
b1011 (
b1110 #
b1110 &
#3345
b11011111 %
#3355
b1100 "
b1100 (
b1111 #
b1111 &
#3360
b11100000 %
#3370
0!
b1110 "
b1110 (
b1110 $
b1110 '
b0 #
b0 &
#3375
b11100001 %
#3385
b1111 "
b1111 (
b1 #
b1 &
#3390
b11100010 %
#3400
1!
b0 "
b0 (
b10 #
b10 &
#3405
b11100011 %
#3415
b1 "
b1 (
b11 #
b11 &
#3420
b11100100 %
#3430
b10 "
b10 (
b100 #
b100 &
#3435
b11100101 %
#3445
b11 "
b11 (
b101 #
b101 &
#3450
b11100110 %
#3460
b100 "
b100 (
b110 #
b110 &
#3465
b11100111 %
#3475
b101 "
b101 (
b111 #
b111 &
#3480
b11101000 %
#3490
b110 "
b110 (
b1000 #
b1000 &
#3495
b11101001 %
#3505
b111 "
b111 (
b1001 #
b1001 &
#3510
b11101010 %
#3520
b1000 "
b1000 (
b1010 #
b1010 &
#3525
b11101011 %
#3535
b1001 "
b1001 (
b1011 #
b1011 &
#3540
b11101100 %
#3550
b1010 "
b1010 (
b1100 #
b1100 &
#3555
b11101101 %
#3565
b1011 "
b1011 (
b1101 #
b1101 &
#3570
b11101110 %
#3580
b1100 "
b1100 (
b1110 #
b1110 &
#3585
b11101111 %
#3595
b1101 "
b1101 (
b1111 #
b1111 &
#3600
b11110000 %
#3610
0!
b1111 "
b1111 (
b1111 $
b1111 '
b0 #
b0 &
#3615
b11110001 %
#3625
1!
b0 "
b0 (
b1 #
b1 &
#3630
b11110010 %
#3640
b1 "
b1 (
b10 #
b10 &
#3645
b11110011 %
#3655
b10 "
b10 (
b11 #
b11 &
#3660
b11110100 %
#3670
b11 "
b11 (
b100 #
b100 &
#3675
b11110101 %
#3685
b100 "
b100 (
b101 #
b101 &
#3690
b11110110 %
#3700
b101 "
b101 (
b110 #
b110 &
#3705
b11110111 %
#3715
b110 "
b110 (
b111 #
b111 &
#3720
b11111000 %
#3730
b111 "
b111 (
b1000 #
b1000 &
#3735
b11111001 %
#3745
b1000 "
b1000 (
b1001 #
b1001 &
#3750
b11111010 %
#3760
b1001 "
b1001 (
b1010 #
b1010 &
#3765
b11111011 %
#3775
b1010 "
b1010 (
b1011 #
b1011 &
#3780
b11111100 %
#3790
b1011 "
b1011 (
b1100 #
b1100 &
#3795
b11111101 %
#3805
b1100 "
b1100 (
b1101 #
b1101 &
#3810
b11111110 %
#3820
b1101 "
b1101 (
b1110 #
b1110 &
#3825
b11111111 %
#3835
b1110 "
b1110 (
b1111 #
b1111 &
#3840
b100000000 %
