Aeolus/src/Registers.v
// Registers

module DFF_4bit ( //DFF used just for buffering signals
    input wire clk,
    input wire [3:0] D,
    output reg [3:0] Q
);

    always @(posedge clk) begin
            Q <= D;
    end

endmodule

module DFF ( //DFF used just for buffering signals
    input wire clk,
    input wire  D,
    output reg  Q
);

    always @(posedge clk) begin
            Q <= D;
    end

endmodule

module EnableDFF_4bit(
    input wire clk,
    input wire enable,
    input wire [3:0] D,
    output reg [3:0] Q
);

    always @(posedge clk) begin
        if (enable) begin
            Q <= D;
        end
    end

endmodule

module ResetEnableDFF_4bit( // synchronous reset
    input wire clk,
    input wire reset,
    input wire enable,
    input wire [3:0] D,
    output reg [3:0] Q
);

    always @(posedge clk) begin
        if (~reset) begin
            if (enable) begin
                Q <= D;
            end 
        end else begin // reset behaviour
            Q <= 0;
        end
    end

endmodule

module ResetDFF_4bit ( // synchronous reset, no enable
    input wire clk,
    input wire reset,
    input wire [3:0] D,
    output reg [3:0] Q
);

    always @(posedge clk) begin
        if (~reset) begin
            Q <= D;
        end else begin // reset behaviour
            Q <= 0;
        end
    end

endmodule

Aeolus/src/ALU.v
// Arithmetic Logic Unit

`include "src/Registers.v"

// Arithmetic Unit Components
/*
               Arithmetic Unit
            /         |         \
        4bitAdder 4bitSubtractor 4bitShifter
        
*/

module ArithmeticLogicUnit (
    input wire       clk,
    input wire       reset,
    input            ADD,
    input            SUB,
    input            LSR,
    input            LSH,
    input            RSH,
    input wire       AND,
    input wire       OR,
    input wire       XOR,
    input wire       INV,
    input wire       CLR,
    input wire [3:0] in1,
    input wire [3:0] in2, 
    output reg [3:0] out,
    output reg       overflow,
    output wire      shiftFlag

);

    wire [3:0] shiftOut, adderOut, subtractorOut;
    wire adderOverflowFlag, subtractorOverflowFlag;
    wire [3:0] andOut;
    wire [3:0] orOut;
    wire [3:0] xorOut;
    wire [3:0] notOut;

    ShiftRegister       sr         (clk, in1, LSR, {LSH,RSH}, shiftOut, shiftFlag);
    CombAdder_4bit      adder      (in1, in2, adderOut, adderOverflowFlag);
    CombSubtractor_4bit subtractor (in1, in2, subtractorOut, subtractorOverflowFlag);
    And_4bit            andGate    (in1, in2, andOut);
    Or_4bit             orGate     (in1, in2, orOut);
    Xor_4bit            xorGate    (in1, in2, xorOut);
    Inv_4bit            notGate    (in1, notOut);


    always @(*) begin // mux for control signals - assumes they won't be sent together
    
        // Arithmetic
        if (ADD) begin
            out = adderOut;
            overflow = adderOverflowFlag;
        end

        if (SUB) begin
            out = subtractorOut;
            overflow = subtractorOverflowFlag;
        end

        if (LSH) begin
            out = shiftOut;
        end

        if (RSH) begin
            out = shiftOut;
        end

        // Logic
        if (AND) begin
            out =  andOut;
            overflow = 0; 
        end

        if (OR) begin
            out =  orOut;
            overflow = 0;
        end

        if (XOR) begin
            out =  xorOut;
            overflow = 0;    
        end

        if (INV) begin
            out =  notOut;
            overflow = 0;    
        end

        if (CLR) begin
            out =  0;
            overflow = 0;    
        end
        
    end

endmodule


module ShiftRegister (  // sequential shift register (D type FF with Enable)
    input wire       clk,
    input wire [3:0] in,
    input wire       loadEnable,
    input      [1:0] shiftState,  //reg
    output reg [3:0] out,
    output reg       flag
);
   
    wire [3:0] dataReg;

    EnableDFF_4bit inShift (clk, loadEnable, in, dataReg); // sequential load

        always @(*) begin
            case (shiftState)    // combinatorial output  
                2: begin      // LSH
                    {flag,out} = dataReg << 1;
                end 
                1: begin // RSH
                    {flag,out} = dataReg >> 1;
                end
                default begin  
                    out = 0;
                end 
            endcase
        end 

endmodule

module FullAdder(
    input wire in1,
    input wire in2,
    input wire carryIn,
    output  sum,
    output  carryOut
);
    assign {carryOut,sum} = in1 + in2; // behavioural description

endmodule

// ripple carry adder 4-bits - not verified
module SyncRippleCarryAdder_4bit (  // synchronous design, hierarchal desgin
    input wire         clk,
    input wire         reset,
    input wire  [3:0]  in1,
    input wire  [3:0]  in2,
    output reg  [3:0]  out,
    output reg         overflow
);
    wire carry1,carry2,carry3,carry4;
    reg c1, c2, c3;

    wire o0, o1, o2, o3;

    FullAdder f1 (in1[0], in2[0], 1'b0, o0, carry1);
    FullAdder f2 (in1[1], in2[1], c1,   o1, carry2);
    FullAdder f3 (in1[2], in2[2], c2,   o2, carry3);
    FullAdder f4 (in1[3], in2[3], c3,   o3, carry4);

    always @(posedge clk) begin
        if (~reset) begin
            c1 <= carry1;
            c2 <= carry2;
            c3 <= carry3;

            out[0] <= o0;
            out[1] <= o1;
            out[2] <= o2;
            out[3] <= o3;
            overflow <= carry4;
        
        end else begin
            c1 <= 0;
            c2 <= 0;
            c3 <= 0;

            out[0] <= 0;
            out[1] <= 0;
            out[2] <= 0;
            out[3] <= 0;
            overflow <= 0;
        end

    end

endmodule

// 4-bit adder
module CombAdder_4bit ( // Conbinational, Behavioural Description
    input wire  [3:0]  in1,
    input wire  [3:0]  in2,
    output reg  [3:0]  out,
    output reg         overflow  
);

    always @(*) begin
        {overflow, out} = in1 + in2;
    end

endmodule

//  4-bit Subtractor
module CombSubtractor_4bit (  // Combinational - Behavioural Description
    input wire  [3:0]  in1,
    input wire  [3:0]  in2,
    output reg  [3:0]  out,
    output reg        overflow  
);

    always @(*) begin
        {overflow, out} = in1 - in2;
    end

endmodule

// 4-bit Adder
module SyncAdder_4bit (  // Synchronous, Behavioural Descriptiion
    input wire         clk,
    input wire         reset,
    input wire  [3:0]  in1,
    input wire  [3:0]  in2,
    output reg  [3:0]  out,
    output reg         overflow  // what does this represent in a subtractionn?
);
    always @(posedge clk) begin
        if (~reset) begin
            {overflow, out} = in1 + in2;
        end else begin
            out = 0;
        end
    end 

endmodule

//4-bit Subtractor
module SyncSubtractor_4bit (  // Synchronous, Behavioural Descriptiion
    input wire         clk,
    input wire         reset,
    input wire  [3:0]  in1,
    input wire  [3:0]  in2,
    output reg  [3:0]  out,
    output reg         overflow  // what does this represent in a subtractionn?
);

    always @(posedge clk ) begin
        if (~reset) begin
            {overflow, out} = in1 - in2;
        end else begin
            out = 0;
        end
    end 

endmodule

// Logic Unit Components

/*         Logic Unit
        /      |       \
      AND      OR       XOR 
*/


//4-bit AND - combinational
module And_4bit(
    input wire [3:0] in1,
    input wire [3:0] in2,
    output wire [3:0] out
);

    assign out = in1 & in2;

endmodule 

// 4-bit OR - combinational
module Or_4bit(
    input wire [3:0] in1,
    input wire [3:0] in2,
    output wire [3:0] out
);

    assign out = in1 | in2;

endmodule

//4 -bit XOR - combinational 
module Xor_4bit (
    input wire [3:0] in1, in2,
    output wire [3:0] out
);

    assign out = in1 ^ in2;

endmodule 

//4 -bit XOR - combinational 
module  Inv_4bit (
    input wire [3:0] in1, 
    output wire [3:0] out
);

    assign out = ~in1;

endmodule

Aeolus/src/Control.v
// Control Modules

// CLK Div to create system CLK 

module clkDiv(
    input wire CLKin,
    output wire CLKout
    );

    parameter COUNTER_SIZE = 64; 
    parameter COUNTER_TARGET = 1;

// T(clkOut) / T(clkin) = Countersize / counter target

  reg[COUNTER_SIZE - 1:0] counter = 0;

   always @(posedge CLKin) begin
        counter <= counter  + 1;
   end

   assign CLKout = counter[COUNTER_TARGET];

endmodule

module Counter_2bit(
    input            clk,
    input            reset,
    input            enable,
    output reg [1:0] value
);

    always @(posedge clk ) begin
        if (~reset) begin
            if (enable) begin
                value <= value + 1;   
            end
        end else begin
            value <= 0;
        end
      
    end


endmodule

// Instruction Decoder to map opcodes to control signals.
// 1762

module InstructionDecoder(
    input  [3:0] instructionIn,
    output       LDA,
    output       LDB,
    output       LDO,
    output       LDSA,
    output       LDSB,
    output       LSH,
    output       RSH,
    output       CLR,
    output       SNZA,
    output       SNZS,
    output       ADD,
    output       SUB,
    output       AND,
    output       OR,
    output       XOR,
    output       INV
);
    // 1-hot control signal encoding
    reg [15:0] ControlSignals; 
    
    always @(*) begin
        ControlSignals = 16'b0000_0000_0000_0001 << instructionIn;
    end

    assign {INV,XOR,OR,AND,SUB,ADD,SNZS,SNZA,CLR,RSH,LSH,LDSB,LDSA,LDO,LDB,LDA} = ControlSignals;
    

endmodule

Aeolus/src/ROM.v
// Program ROM 
// ROM : Acts as a insturction storage unit for the CPU

module ProgramROM (    // ROM for the main system 
    input  wire [3:0] addressIn,
    output reg  [3:0] dataOut
);

    always @(*) begin


        case (addressIn)
            0: begin
                dataOut = 4'b0000; //LDA
            end

            1: begin
                dataOut = 4'b0001; //LDB
            end

            2: begin
                dataOut = 4'b1010; //ADD
            end

            3: begin
                dataOut = 4'b0010; //LD O
            end

            4: begin
                dataOut = 4'b1011; //SUB
            end

            5: begin
                dataOut = 4'b0010; //LDO
            end
            
            6: begin
                dataOut = 4'b1110; //XOR
            end

            7: begin
                 dataOut = 4'b0010; //LDO
            end

            8: begin
                 dataOut = 4'b0011; //LDS A
            end

            9: begin
                 dataOut = 4'b0110; //RSH
            end

            10: begin
                 dataOut = 4'b1000; //SNZ A
            end

            11: begin
                 dataOut = 4'b0010; //LDS B
            end

            12: begin
                 dataOut = 4'b0010; //LSH
            end

            13: begin
                 dataOut = 4'b0100; //SNZ S
            end

            14: begin
                 dataOut = 4'b0010; //LDO
            end

            default: begin
                dataOut = 5'b0111; //CLR - basically a NOP operation.
            end

        endcase
    
    end

endmodule

// Program ROM 

module ProgramROM2 (  // Rom built for specific test case 
    input  wire [3:0] addressIn,
    output reg  [3:0] dataOut
);

    always @(*) begin

        case (addressIn)
            0: begin
                dataOut = 4'b0000; //LDA
            end

            1: begin
                dataOut = 4'b0001; //LDB
            end

            2: begin
                 dataOut = 4'b1010; //ADD
            end

            
            3: begin
                 dataOut = 4'b0010; //LDO
            end

            4: begin
                 dataOut = 4'b1011; //SUB
            end

            5: begin
                 dataOut = 4'b0010; //LDO
            end

            6: begin
                 dataOut = 4'b1110; //XOR
            end

            7: begin
                 dataOut = 4'b0010; //LDO
            end

            default: begin
                dataOut = 5'b0111; //CLR - basically a NOP operation.
            end

        endcase
    
    end

endmodule

module ProgramROM3  ( // Conditional Test
    input  wire [3:0] addressIn,
    output reg  [3:0] dataOut
);

    always @(*) begin

        case (addressIn)
            0: begin
                dataOut = 4'b0000; //LDA
            end

            1: begin
                dataOut = 4'b0001; //LDB
            end

            2: begin
                 dataOut= 4'b1010; //ADD
            end
            
            3: begin
                 dataOut = 4'b0010; //LDO
            end

            4: begin
                dataOut = 4'b0100; // LDSB
            end

            5: begin
                 dataOut = 4'b0101; // LSH
            end

            6: begin
                 dataOut = 4'b1000; // SNZA
            end

            7: begin
                 dataOut = 4'b0010; // LDO
            end

            default: begin
                dataOut = 5'b0111; //CLR - basically a NOP operation.
            end

        endcase
    
    end

endmodule

Aeolus/src/Top.v
`include "src/ALU.v"
`include "src/Control.v"
`include "src/ROM.v"

//  Multi-cycle implimentation

//  Done: make everything single cycle 


//  K 
//  todo: comment and document the design so far.
//  todo: Test: Shift, Load Shift Reg 

// J
//  todo: impliment the example ROM.
//  todo: Test: conditional instructions

// BOTH .. later ...
//  todo: optimise the design for area (ALU reduction / Get rid of the increment adder).

//  Extensions:
//  todo: develop an extended instruction set using multi cycle
//  todo: impliment NOP 
//  todo: develop a pipelined desgin with extended IS


module AeolusCPUTop (

    input wire       boardCLK,
    input wire       reset,
    input wire [7:0] switches,
    output reg [3:0] cpuOut
);

    wire clk;

    // 100MHZ -> x MHz CLK
    clkDiv clkdiv(  
        .CLKin(boardCLK),
        .CLKout(clk)
    );

    // Program Counter 
    wire [3:0] PCin;
    wire [3:0] INCout;
    wire [3:0] PCout;
    wire PCoverflow;
    reg  incrementValue;
    
    ResetEnableDFF_4bit PC (clk, reset, 1'b1 , PCin, PCout);
    CombAdder_4bit inc (PCout, 4'b0001, PCin , PCoverflow ); 

    // ROM inputs and outputs
    wire [3:0] opcode;

    ProgramROM3 rom (
     .addressIn(PCout),
     .dataOut(opcode)
     );

    // instruction decoder
    InstructionDecoder decoder (
        .instructionIn(opcode),
        .LDA  (_LDA),
        .LDB  (_LDB),
        .LDO  (_LDO),
        .LDSA (_LDSA),
        .LDSB (_LDSB),
        .LSH  (_LSH),
        .RSH  (_RSH),
        .CLR  (_CLR),
        .SNZA (_SNZA),
        .SNZS (_SNZS),
        .ADD  (_ADD),
        .SUB  (_SUB),
        .AND  (_AND),
        .OR   (_OR),
        .XOR  (_XOR),
        .INV  (_INV)
    );

    // Regsiter File

    // A register
    wire       _LDA;
    wire [3:0] Aout;

    EnableDFF_4bit RegA (clk, _LDA, switches[7:4], Aout);

    // B register
    wire       _LDB;
    wire [3:0] Bout;

    EnableDFF_4bit RegB (clk, _LDB, switches[3:0], Bout);

    // ALU Instructions
    wire _LDSA, _LDSB;

    wire _ADD, _SUB, _LSR, _LSH, _RSH,_AND, _OR, _XOR, _INV;

    assign _LSR = _LDSA || _LDSB;
    // ALU control
    reg _ADDin;
    reg _shiftFlag;
    wire SF;

    // ALU inputs
    reg [3:0] in1;
    reg [3:0] in2;

    always @(*) begin // MUX for ALU inputs , different for some  operations e.g (SNZA, SNZB, LDSA and LDSB)
        
        _shiftFlag = SF;

        if (_SNZA | _SNZS ) begin
            _ADDin = 1;
        end else  begin
            _ADDin = _ADD;
        end

        if (_SNZA == 1  && _shiftFlag == 1 || _LDSA)  begin
            in1 = Aout;
            in2 = 0;
        end else if (_LDSB) begin
            in1 = Bout;
            in2 = 0;
        end else if ((_SNZS == 1 && _shiftFlag == 1)) begin
            in1 = alu.shiftOut ;
            in2 = 0;
        end else begin // non conditional instructinos
            in1 = Aout;
            in2 = Bout;
        end

    end 

    wire [3:0] aluOut;
    wire       OF;

    // alu
    ArithmeticLogicUnit alu( 
        .clk(clk),
        .reset(reset),
        .ADD(_ADDin),
        .SUB(_SUB),
        .LSR(_LSR),
        .LSH(_LSH),
        .RSH(_RSH),
        .AND(_AND),
        .OR (_OR),
        .XOR(_XOR),
        .INV(_INV),
        .CLR(_CLR),
        .in1(in1),
        .in2(in2), 
        .out(aluOut),
        .overflow(OF),
        .shiftFlag(SF)
    );

    wire       _CLR;
    wire [3:0] ACCout;

    // accumulator
    ResetDFF_4bit ACC (clk, _CLR || reset, aluOut, ACCout);
    
    wire      _LDO;
    wire      _LDO2;
    wire [3:0] Oout;
    
    // buffer and output register
    DFF LDOBuff (clk, _LDO,_LDO2);
    EnableDFF_4bit RegO (clk, _LDO, ACCout, Oout);

    always @(*) begin
        cpuOut = Oout;
    end

endmodule

Aeolus/test/cpuTB.v
// Logic Testbench

`timescale 1ns/1ns
`include "src/Top.v"

`define assert(signal, value) if (signal !== value) begin  $display("ASSERTION FAILED for OPCODE: %4b at time %0t ns : %m signal  !=  value expected: %5b, got: %5b", OPCODE , $time , value, signal); $finish; end

module CPUTb();

    reg        CLK;
    reg        RESET;
    reg  [7:0] SWITCHES;
    wire [3:0] CPU_OUT;

    integer i;

    AeolusCPUTop uut(
        .boardCLK(CLK),
        .reset(RESET),
        .switches(SWITCHES),
        .cpuOut(CPU_OUT)
    );

    initial begin

        $dumpfile("test/vcd/CPUadddump.vcd");
        $dumpvars(0, CPUTb);
        
        CLK = 1; RESET = 1; SWITCHES[7:0] = 8'b0011_1110; 
        #20 RESET = 0;

        #1000 RESET = 1;
        #100 $display("program complete!"); $finish; 
    end

    always  begin
            #5 CLK = ~CLK;
        end

endmodule

Aeolus/test/vcd/CPUadddump.vcd
$date
	Fri Feb 21 10:55:27 2025
$end
$version
	Icarus Verilog
$end
$timescale
	1ns
$end
$scope module CPUTb $end
$var wire 4 ! CPU_OUT [3:0] $end
$var reg 1 " CLK $end
$var reg 1 # RESET $end
$var reg 8 $ SWITCHES [7:0] $end
$scope module uut $end
$var wire 1 % _LSR $end
$var wire 1 " boardCLK $end
$var wire 1 # reset $end
$var wire 8 & switches [7:0] $end
$var wire 4 ' opcode [3:0] $end
$var wire 1 ( clk $end
$var wire 4 ) aluOut [3:0] $end
$var wire 1 * _XOR $end
$var wire 1 + _SUB $end
$var wire 1 , _SNZS $end
$var wire 1 - _SNZA $end
$var wire 1 . _RSH $end
$var wire 1 / _OR $end
$var wire 1 0 _LSH $end
$var wire 1 1 _LDSB $end
$var wire 1 2 _LDSA $end
$var wire 1 3 _LDO2 $end
$var wire 1 4 _LDO $end
$var wire 1 5 _LDB $end
$var wire 1 6 _LDA $end
$var wire 1 7 _INV $end
$var wire 1 8 _CLR $end
$var wire 1 9 _AND $end
$var wire 1 : _ADD $end
$var wire 1 ; SF $end
$var wire 1 < PCoverflow $end
$var wire 4 = PCout [3:0] $end
$var wire 4 > PCin [3:0] $end
$var wire 4 ? Oout [3:0] $end
$var wire 1 @ OF $end
$var wire 4 A Bout [3:0] $end
$var wire 4 B Aout [3:0] $end
$var wire 4 C ACCout [3:0] $end
$var reg 1 D _ADDin $end
$var reg 1 E _shiftFlag $end
$var reg 4 F cpuOut [3:0] $end
$var reg 4 G in1 [3:0] $end
$var reg 4 H in2 [3:0] $end
$scope module ACC $end
$var wire 1 I reset $end
$var wire 1 ( clk $end
$var wire 4 J D [3:0] $end
$var reg 4 K Q [3:0] $end
$upscope $end
$scope module LDOBuff $end
$var wire 1 ( clk $end
$var wire 1 4 D $end
$var reg 1 3 Q $end
$upscope $end
$scope module PC $end
$var wire 1 L enable $end
$var wire 1 # reset $end
$var wire 1 ( clk $end
$var wire 4 M D [3:0] $end
$var reg 4 N Q [3:0] $end
$upscope $end
$scope module RegA $end
$var wire 4 O D [3:0] $end
$var wire 1 6 enable $end
$var wire 1 ( clk $end
$var reg 4 P Q [3:0] $end
$upscope $end
$scope module RegB $end
$var wire 4 Q D [3:0] $end
$var wire 1 5 enable $end
$var wire 1 ( clk $end
$var reg 4 R Q [3:0] $end
$upscope $end
$scope module RegO $end
$var wire 4 S D [3:0] $end
$var wire 1 4 enable $end
$var wire 1 ( clk $end
$var reg 4 T Q [3:0] $end
$upscope $end
$scope module alu $end
$var wire 1 D ADD $end
$var wire 1 % LSR $end
$var wire 4 U in1 [3:0] $end
$var wire 4 V in2 [3:0] $end
$var wire 1 # reset $end
$var wire 4 W xorOut [3:0] $end
$var wire 1 X subtractorOverflowFlag $end
$var wire 4 Y subtractorOut [3:0] $end
$var wire 4 Z shiftOut [3:0] $end
$var wire 1 ; shiftFlag $end
$var wire 4 [ orOut [3:0] $end
$var wire 4 \ notOut [3:0] $end
$var wire 1 ( clk $end
$var wire 4 ] andOut [3:0] $end
$var wire 1 ^ adderOverflowFlag $end
$var wire 4 _ adderOut [3:0] $end
$var wire 1 * XOR $end
$var wire 1 + SUB $end
$var wire 1 . RSH $end
$var wire 1 / OR $end
$var wire 1 0 LSH $end
$var wire 1 7 INV $end
$var wire 1 8 CLR $end
$var wire 1 9 AND $end
$var reg 4 ` out [3:0] $end
$var reg 1 @ overflow $end
$scope module adder $end
$var wire 4 a in1 [3:0] $end
$var wire 4 b in2 [3:0] $end
$var reg 4 c out [3:0] $end
$var reg 1 ^ overflow $end
$upscope $end
$scope module andGate $end
$var wire 4 d in1 [3:0] $end
$var wire 4 e in2 [3:0] $end
$var wire 4 f out [3:0] $end
$upscope $end
$scope module notGate $end
$var wire 4 g in1 [3:0] $end
$var wire 4 h out [3:0] $end
$upscope $end
$scope module orGate $end
$var wire 4 i in1 [3:0] $end
$var wire 4 j in2 [3:0] $end
$var wire 4 k out [3:0] $end
$upscope $end
$scope module sr $end
$var wire 4 l in [3:0] $end
$var wire 1 % loadEnable $end
$var wire 2 m shiftState [1:0] $end
$var wire 4 n dataReg [3:0] $end
$var wire 1 ( clk $end
$var reg 1 ; flag $end
$var reg 4 o out [3:0] $end
$scope module inShift $end
$var wire 4 p D [3:0] $end
$var wire 1 % enable $end
$var wire 1 ( clk $end
$var reg 4 q Q [3:0] $end
$upscope $end
$upscope $end
$scope module subtractor $end
$var wire 4 r in1 [3:0] $end
$var wire 4 s in2 [3:0] $end
$var reg 4 t out [3:0] $end
$var reg 1 X overflow $end
$upscope $end
$scope module xorGate $end
$var wire 4 u in1 [3:0] $end
$var wire 4 v in2 [3:0] $end
$var wire 4 w out [3:0] $end
$upscope $end
$upscope $end
$scope module clkdiv $end
$var wire 1 " CLKin $end
$var wire 1 ( CLKout $end
$var parameter 32 x COUNTER_SIZE $end
$var parameter 32 y COUNTER_TARGET $end
$var reg 64 z counter [63:0] $end
$upscope $end
$scope module decoder $end
$var wire 4 { instructionIn [3:0] $end
$var wire 1 * XOR $end
$var wire 1 + SUB $end
$var wire 1 , SNZS $end
$var wire 1 - SNZA $end
$var wire 1 . RSH $end
$var wire 1 / OR $end
$var wire 1 0 LSH $end
$var wire 1 1 LDSB $end
$var wire 1 2 LDSA $end
$var wire 1 4 LDO $end
$var wire 1 5 LDB $end
$var wire 1 6 LDA $end
$var wire 1 7 INV $end
$var wire 1 8 CLR $end
$var wire 1 9 AND $end
$var wire 1 : ADD $end
$var reg 16 | ControlSignals [15:0] $end
$upscope $end
$scope module inc $end
$var wire 4 } in1 [3:0] $end
$var wire 4 ~ in2 [3:0] $end
$var reg 4 !" out [3:0] $end
$var reg 1 < overflow $end
$upscope $end
$scope module rom $end
$var wire 4 "" addressIn [3:0] $end
$var reg 4 #" dataOut [3:0] $end
$upscope $end
$upscope $end
$upscope $end
$enddefinitions $end
$comment Show the parameter values. $end
$dumpall
b1 y
b1000000 x
$end
#0
$dumpvars
bx #"
bx ""
bx !"
b1 ~
bx }
bx |
bx {
b1 z
bx w
bx v
bx u
bx t
bx s
bx r
bx q
bx p
bx o
bx n
bx m
bx l
bx k
bx j
bx i
bx h
bx g
bx f
bx e
bx d
bx c
bx b
bx a
bx `
bx _
x^
bx ]
bx \
bx [
bx Z
bx Y
xX
bx W
bx V
bx U
bx T
bx S
bx R
b1110 Q
bx P
b11 O
bx N
bx M
1L
bx K
bx J
1I
bx H
bx G
bx F
xE
xD
bx C
bx B
bx A
x@
bx ?
bx >
bx =
x<
x;
x:
x9
x8
x7
x6
x5
x4
x3
x2
x1
x0
x/
x.
x-
x,
x+
x*
bx )
0(
bx '
b111110 &
x%
b111110 $
1#
1"
bx !
$end
#5
0"
#10
b0 Z
b0 o
0D
0%
07
0*
0/
09
0+
0:
0,
0-
08
0.
b0 m
00
01
02
04
05
16
b1 |
0<
b1 >
b1 M
b1 !"
b0 '
b0 {
b0 #"
b0 =
b0 N
b0 }
b0 ""
b0 C
b0 K
b0 S
1(
b10 z
1"
#15
0"
#20
b11 z
0I
1"
0#
#25
0"
#30
0(
b100 z
1"
#35
0"
#40
b101 z
1"
#45
0"
#50
15
06
b0xx ]
b0xx f
b1100 \
b1100 h
bx11 [
bx11 k
b10 |
b11 G
b11 U
b11 a
b11 d
b11 g
b11 i
b11 l
b11 p
b11 r
b11 u
b10 >
b10 M
b10 !"
b1 '
b1 {
b1 #"
03
bx C
bx K
bx S
b11 B
b11 P
b1 =
b1 N
b1 }
b1 ""
1(
b110 z
1"
#55
0"
#60
b111 z
1"
#65
0"
#70
0(
b1000 z
1"
#75
0"
#80
b1001 z
1"
#85
0"
#90
1@
b1 )
b1 J
b1 `
1D
1:
05
b10000000000 |
1^
b1 _
b1 c
1X
b101 Y
b101 t
b10 ]
b10 f
b1111 [
b1111 k
b1101 W
b1101 w
b11 >
b11 M
b11 !"
b1010 '
b1010 {
b1010 #"
b1110 H
b1110 V
b1110 b
b1110 e
b1110 j
b1110 s
b1110 v
b10 =
b10 N
b10 }
b10 ""
b1110 A
b1110 R
1(
b1010 z
1"
#95
0"
#100
b1011 z
1"
#105
0"
#110
0(
b1100 z
1"
#115
0"
#120
b1101 z
1"
#125
0"
#130
0D
0:
14
b100 |
b100 >
b100 M
b100 !"
b10 '
b10 {
b10 #"
b1 C
b1 K
b1 S
b11 =
b11 N
b11 }
b11 ""
1(
b1110 z
1"
#135
0"
#140
b1111 z
1"
#145
0"
#150
0(
b10000 z
1"
#155
0"
#160
b10001 z
1"
#165
0"
#170
0X
b1110 Y
b1110 t
0^
b1110 _
b1110 c
b0 ]
b0 f
b1 \
b1 h
b1110 [
b1110 k
b1110 W
b1110 w
b0 H
b0 V
b0 b
b0 e
b0 j
b0 s
b0 v
b1110 G
b1110 U
b1110 a
b1110 d
b1110 g
b1110 i
b1110 l
b1110 p
b1110 r
b1110 u
1%
11
04
b10000 |
b101 >
b101 M
b101 !"
b100 '
b100 {
b100 #"
b1 !
b1 F
b100 =
b100 N
b100 }
b100 ""
13
b1 ?
b1 T
1(
b10010 z
1"
#175
0"
#180
b10011 z
1"
#185
0"
#190
0(
b10100 z
1"
#195
0"
#200
b10101 z
1"
#205
0"
#210
1E
1^
b1 _
b1 c
1X
b101 Y
b101 t
b10 ]
b10 f
b1100 \
b1100 h
b1111 [
b1111 k
b1101 W
b1101 w
1;
b1100 Z
b1100 o
b1100 )
b1100 J
b1100 `
b1110 H
b1110 V
b1110 b
b1110 e
b1110 j
b1110 s
b1110 v
b11 G
b11 U
b11 a
b11 d
b11 g
b11 i
b11 l
b11 p
b11 r
b11 u
0%
b10 m
10
01
b100000 |
b110 >
b110 M
b110 !"
b101 '
b101 {
b101 #"
03
b1110 n
b1110 q
b101 =
b101 N
b101 }
b101 ""
1(
b10110 z
1"
#215
0"
#220
b10111 z
1"
#225
0"
#230
0(
b11000 z
1"
#235
0"
#240
b11001 z
1"
#245
0"
#250
0@
0X
b11 Y
b11 t
0^
b11 _
b11 c
b0 ]
b0 f
b11 [
b11 k
b11 W
b11 w
b11 )
b11 J
b11 `
b0 H
b0 V
b0 b
b0 e
b0 j
b0 s
b0 v
1D
b0 Z
b0 o
1-
b0 m
00
b100000000 |
b111 >
b111 M
b111 !"
b1000 '
b1000 {
b1000 #"
b110 =
b110 N
b110 }
b110 ""
b1100 C
b1100 K
b1100 S
1(
b11010 z
1"
#255
0"
#260
b11011 z
1"
#265
0"
#270
0(
b11100 z
1"
#275
0"
#280
b11101 z
1"
#285
0"
#290
1^
b1 _
b1 c
1X
b101 Y
b101 t
b10 ]
b10 f
b1111 [
b1111 k
b1101 W
b1101 w
b1110 H
b1110 V
b1110 b
b1110 e
b1110 j
b1110 s
b1110 v
0D
0-
14
b100 |
b1000 >
b1000 M
b1000 !"
b10 '
b10 {
b10 #"
b11 C
b11 K
b11 S
b111 =
b111 N
b111 }
b111 ""
1(
b11110 z
1"
#295
0"
#300
b11111 z
1"
#305
0"
#310
0(
b100000 z
1"
#315
0"
#320
b100001 z
1"
#325
0"
#330
1I
b0 )
b0 J
b0 `
18
04
b10000000 |
b1001 >
b1001 M
b1001 !"
b111 '
b111 {
b111 #"
b11 !
b11 F
b1000 =
b1000 N
b1000 }
b1000 ""
13
b11 ?
b11 T
1(
b100010 z
1"
#335
0"
#340
b100011 z
1"
#345
0"
#350
0(
b100100 z
1"
#355
0"
#360
b100101 z
1"
#365
0"
#370
b1010 >
b1010 M
b1010 !"
03
b0 C
b0 K
b0 S
b1001 =
b1001 N
b1001 }
b1001 ""
1(
b100110 z
1"
#375
0"
#380
b100111 z
1"
#385
0"
#390
0(
b101000 z
1"
#395
0"
#400
b101001 z
1"
#405
0"
#410
b1011 >
b1011 M
b1011 !"
b1010 =
b1010 N
b1010 }
b1010 ""
1(
b101010 z
1"
#415
0"
#420
b101011 z
1"
#425
0"
#430
0(
b101100 z
1"
#435
0"
#440
b101101 z
1"
#445
0"
#450
b1100 >
b1100 M
b1100 !"
b1011 =
b1011 N
b1011 }
b1011 ""
1(
b101110 z
1"
#455
0"
#460
b101111 z
1"
#465
0"
#470
0(
b110000 z
1"
#475
0"
#480
b110001 z
1"
#485
0"
#490
b1101 >
b1101 M
b1101 !"
b1100 =
b1100 N
b1100 }
b1100 ""
1(
b110010 z
1"
#495
0"
#500
b110011 z
1"
#505
0"
#510
0(
b110100 z
1"
#515
0"
#520
b110101 z
1"
#525
0"
#530
b1110 >
b1110 M
b1110 !"
b1101 =
b1101 N
b1101 }
b1101 ""
1(
b110110 z
1"
#535
0"
#540
b110111 z
1"
#545
0"
#550
0(
b111000 z
1"
#555
0"
#560
b111001 z
1"
#565
0"
#570
b1111 >
b1111 M
b1111 !"
b1110 =
b1110 N
b1110 }
b1110 ""
1(
b111010 z
1"
#575
0"
#580
b111011 z
1"
#585
0"
#590
0(
b111100 z
1"
#595
0"
#600
b111101 z
1"
#605
0"
#610
1<
b0 >
b0 M
b0 !"
b1111 =
b1111 N
b1111 }
b1111 ""
1(
b111110 z
1"
#615
0"
#620
b111111 z
1"
#625
0"
#630
0(
b1000000 z
1"
#635
0"
#640
b1000001 z
1"
#645
0"
#650
0I
08
16
b1 |
0<
b1 >
b1 M
b1 !"
b0 '
b0 {
b0 #"
b0 =
b0 N
b0 }
b0 ""
1(
b1000010 z
1"
#655
0"
#660
b1000011 z
1"
#665
0"
#670
0(
b1000100 z
1"
#675
0"
#680
b1000101 z
1"
#685
0"
#690
15
06
b10 |
b10 >
b10 M
b10 !"
b1 '
b1 {
b1 #"
b1 =
b1 N
b1 }
b1 ""
1(
b1000110 z
1"
#695
0"
#700
b1000111 z
1"
#705
0"
#710
0(
b1001000 z
1"
#715
0"
#720
b1001001 z
1"
#725
0"
#730
1@
b1 )
b1 J
b1 `
1D
1:
05
b10000000000 |
b11 >
b11 M
b11 !"
b1010 '
b1010 {
b1010 #"
b10 =
b10 N
b10 }
b10 ""
1(
b1001010 z
1"
#735
0"
#740
b1001011 z
1"
#745
0"
#750
0(
b1001100 z
1"
#755
0"
#760
b1001101 z
1"
#765
0"
#770
0D
0:
14
b100 |
b100 >
b100 M
b100 !"
b10 '
b10 {
b10 #"
b1 C
b1 K
b1 S
b11 =
b11 N
b11 }
b11 ""
1(
b1001110 z
1"
#775
0"
#780
b1001111 z
1"
#785
0"
#790
0(
b1010000 z
1"
#795
0"
#800
b1010001 z
1"
#805
0"
