Aeolus/src/Registers.v
// Registers

module DFF_4bit ( //DFF used just for buffering signals
    input wire clk,
    input wire [3:0] D,
    output reg [3:0] Q
);

    always @(posedge clk) begin
            Q <= D;
    end

endmodule

module DFF ( //DFF used just for buffering signals
    input wire clk,
    input wire  D,
    output reg  Q
);

    always @(posedge clk) begin
            Q <= D;
    end

endmodule

module EnableDFF_4bit(
    input wire clk,
    input wire enable,
    input wire [3:0] D,
    output reg [3:0] Q
);

    always @(posedge clk) begin
        if (enable) begin
            Q <= D;
        end
    end

endmodule

module ResetEnableDFF_4bit( // synchronous reset
    input wire clk,
    input wire reset,
    input wire enable,
    input wire [3:0] D,
    output reg [3:0] Q
);

    always @(posedge clk) begin
        if (~reset) begin
            if (enable) begin
                Q <= D;
            end 
        end else begin // reset behaviour
            Q <= 0;
        end
    end

endmodule

module ResetDFF_4bit ( // synchronous reset, no enable
    input wire clk,
    input wire reset,
    input wire [3:0] D,
    output reg [3:0] Q
);

    always @(posedge clk) begin
        if (~reset) begin
            Q <= D;
        end else begin // reset behaviour
            Q <= 0;
        end
    end

endmodule

Aeolus/src/ALU.v
// Arithmetic Logic Unit

`include "src/Registers.v"

// Arithmetic Unit Components
/*
               Arithmetic Unit
            /         |         \
        4bitAdder 4bitSubtractor 4bitShifter
        
*/

module ArithmeticLogicUnit (
    input wire       clk,
    input wire       reset,
    input            ADD,
    input            SUB,
    input wire       AND,
    input wire       OR,
    input wire       XOR,
    input wire       INV,
    input wire       CLR,
    input wire [DATA_WIDTH-1:0] in1,
    input wire [DATA_WIDTH-1:0] in2, 
    output reg [DATA_WIDTH-1:0] out,
    output reg       overflow,
    output wire      shiftFlag

);

    parameter DATA_WIDTH = 8;

    wire [3:0] shiftOut;
    wire [7:0] adderOut, subtractorOut;
    wire adderOverflowFlag, subtractorOverflowFlag;
    wire [3:0] andOut;
    wire [3:0] orOut;
    wire [3:0] xorOut;
    wire [3:0] notOut;

    CombAdder           adder      (in1, in2, adderOut, adderOverflowFlag); defparam adder.DATA_WIDTH=8;
    CombSubtractor      subtractor (in1, in2, subtractorOut, subtractorOverflowFlag); defparam subtractor.DATA_WIDTH=8;

    And_4bit            andGate    (in1[3:0], in2[3:0], andOut);
    Or_4bit             orGate     (in1[3:0], in2[3:0], orOut);
    Xor_4bit            xorGate    (in1[3:0], in2[3:0], xorOut);
    Inv_4bit            notGate    (in1[3:0], notOut);

    always @(*) begin // mux for control signals - assumes they won't be sent together
    
    if (~reset) begin
        // Arithmetic
        if (ADD) begin
            out = adderOut;
            overflow = adderOverflowFlag;
        end

        else if (SUB) begin
            out = subtractorOut;
            overflow = subtractorOverflowFlag;
        end

        // Logic
        else if (AND) begin
            out =  andOut;
            overflow = 0; 
        end

        else if (OR) begin
            out =  orOut;
            overflow = 0;
        end

        else if (XOR) begin
            out =  xorOut;
            overflow = 0;    
        end

        else if (INV) begin
            out =  notOut;
            overflow = 0;    
        end

        else if (CLR) begin
            out =  0;
            overflow = 0;    
        end
            
        end else begin
            out = 0;
            overflow = 0;
        end
    end


endmodule


module FullAdder (
    input wire in1,
    input wire in2,
    input wire carryIn,
    output  sum,
    output  carryOut
);
    assign {carryOut,sum} = in1 + in2; // behavioural description

endmodule

// ripple carry adder 4-bits - not verified
module SyncRippleCarryAdder_4bit (  // synchronous design, hierarchal desgin
    input wire         clk,
    input wire         reset,
    input wire  [3:0]  in1,
    input wire  [3:0]  in2,
    output reg  [3:0]  out,
    output reg         overflow
);
    wire carry1,carry2,carry3,carry4;
    reg c1, c2, c3;

    wire o0, o1, o2, o3;

    FullAdder f1 (in1[0], in2[0], 1'b0, o0, carry1);
    FullAdder f2 (in1[1], in2[1], c1,   o1, carry2);
    FullAdder f3 (in1[2], in2[2], c2,   o2, carry3);
    FullAdder f4 (in1[3], in2[3], c3,   o3, carry4);

    always @(posedge clk) begin
        if (~reset) begin
            c1 <= carry1;
            c2 <= carry2;
            c3 <= carry3;

            out[0] <= o0;
            out[1] <= o1;
            out[2] <= o2;
            out[3] <= o3;
            overflow <= carry4;
        
        end else begin
            c1 <= 0;
            c2 <= 0;
            c3 <= 0;

            out[0] <= 0;
            out[1] <= 0;
            out[2] <= 0;
            out[3] <= 0;
            overflow <= 0;
        end

    end

endmodule

// paramatreised size for input/output

module CombAdder (  // Conbinational, Behavioural Description
    input wire  [DATA_WIDTH - 1:0]  in1,
    input wire  [DATA_WIDTH - 1:0]  in2,
    output reg  [DATA_WIDTH - 1:0]  out,
    output reg                      overflow  
);
    parameter DATA_WIDTH  = 4; //4-bit by default;

    always @(*) begin
        {overflow, out} = in1 + in2;
    end

endmodule

//  4-bit Subtractor
module CombSubtractor (  // Combinational - Behavioural Description
    input wire  [DATA_WIDTH - 1:0]  in1,
    input wire  [DATA_WIDTH - 1:0]  in2,
    output reg  [DATA_WIDTH - 1:0]  out,
    output reg                      overflow  
);
    parameter DATA_WIDTH  = 4; //4-bit by default;

    always @(*) begin
        {overflow, out} = in1 - in2;
    end

endmodule


// 4-bit Modules

module CombAdder_4bit ( // Conbinational, Behavioural Description
    input wire  [3:0]  in1,
    input wire  [3:0]  in2,
    output reg  [3:0]  out,
    output reg         overflow  
);

    always @(*) begin
        {overflow, out} = in1 + in2;
    end

endmodule

//  4-bit Subtractor
module CombSubtractor_4bit (  // Combinational - Behavioural Description
    input wire  [3:0]  in1,
    input wire  [3:0]  in2,
    output reg  [3:0]  out,
    output reg        overflow  
);

    always @(*) begin
        {overflow, out} = in1 - in2;
    end

endmodule

// 4-bit Adder
module SyncAdder_4bit (  // Synchronous, Behavioural Descriptiion
    input wire         clk,
    input wire         reset,
    input wire  [3:0]  in1,
    input wire  [3:0]  in2,
    output reg  [3:0]  out,
    output reg         overflow  // what does this represent in a subtractionn?
);
    always @(posedge clk) begin
        if (~reset) begin
            {overflow, out} = in1 + in2;
        end else begin
            out = 0;
        end
    end 

endmodule

//4-bit Subtractor
module SyncSubtractor_4bit (  // Synchronous, Behavioural Descriptiion
    input wire         clk,
    input wire         reset,
    input wire  [3:0]  in1,
    input wire  [3:0]  in2,
    output reg  [3:0]  out,
    output reg         overflow  // what does this represent in a subtractionn?
);

    always @(posedge clk ) begin
        if (~reset) begin
            {overflow, out} = in1 - in2;
        end else begin
            out = 0;
        end
    end 

endmodule


// Logic Unit Components

/*            Logic Unit
        /      |        |     \  
      AND      OR       XOR    INV
*/


//4-bit AND - combinational
module And_4bit(
    input wire [3:0] in1,
    input wire [3:0] in2,
    output wire [3:0] out
);

    assign out = in1 & in2;

endmodule 

// 4-bit OR - combinational
module Or_4bit(
    input wire [3:0] in1,
    input wire [3:0] in2,
    output wire [3:0] out
);

    assign out = in1 | in2;

endmodule

//4 -bit XOR - combinational 
module Xor_4bit (
    input wire [3:0] in1, in2,
    output wire [3:0] out
);

    assign out = in1 ^ in2;

endmodule 

//4 -bit XOR - combinational 
module  Inv_4bit (
    input wire [3:0] in1, 
    output wire [3:0] out
);

    assign out = ~in1;

endmodule

Aeolus/test/logicTB.v

//Logic Testbench
`include "src/ALU.v"

`define assert(signal, value) if (signal !== value) begin  $display("ASSERTION FAILED in %m: signal != value -> %d != %d", signal, value);  end

module LogicTb();

    reg        CLK;
    reg        RESET;
    reg  [3:0] IN1, IN2;
    wire [3:0] AND_OUT, OR_OUT, XOR_OUT;
    wire       OVERFLOW;
    
    integer i;

    And_4bit a (IN1, IN2, AND_OUT);
    Or_4bit o  (IN1, IN2, OR_OUT);
    Xor_4bit x (IN1, IN2, XOR_OUT);

    initial begin

        $dumpfile("test/vcd/logicgatesdump.vcd");
        $dumpvars(0, LogicTb);
        
        IN1 = 0; IN2 = 0; 

        $display("4-Bit Logic Gates Test");

       //$display("   in1   |  in2     |  actual    |  expected");

        for (i = 0; i < 256 ; i = i + 1) begin

            #10 {IN2, IN1} = i[7:0];
            //#5  $display("  %4b    |   %4b  |   %4b   |   %5b   " ,IN1, IN2,  (i[3:0] + i[7:4]) , {OVERFLOW,OUT} );
            #5  `assert({AND_OUT}, (i[3:0] & i[7:4]));    // assert that the result is the AND operation
                `assert({OR_OUT},  (i[3:0] | i[7:4]));    // assert that the result is the OR operation
                `assert({XOR_OUT}, (i[3:0] ^ i[7:4]));    // assert that the result is the XOR operation
        end

        $display("TEST SUCCESSFUL!"); $finish; 
    end

endmodule

Aeolus/test/vcd/logicgatesdump.vcd
$date
	Tue Feb 18 14:59:50 2025
$end
$version
	Icarus Verilog
$end
$timescale
	1s
$end
$scope module LogicTb $end
$var wire 4 ! XOR_OUT [3:0] $end
$var wire 4 " OR_OUT [3:0] $end
$var wire 4 # AND_OUT [3:0] $end
$var reg 4 $ IN1 [3:0] $end
$var reg 4 % IN2 [3:0] $end
$var integer 32 & i [31:0] $end
$scope module a $end
$var wire 4 ' in1 [3:0] $end
$var wire 4 ( in2 [3:0] $end
$var wire 4 ) out [3:0] $end
$upscope $end
$scope module o $end
$var wire 4 * in1 [3:0] $end
$var wire 4 + in2 [3:0] $end
$var wire 4 , out [3:0] $end
$upscope $end
$scope module x $end
$var wire 4 - in1 [3:0] $end
$var wire 4 . in2 [3:0] $end
$var wire 4 / out [3:0] $end
$upscope $end
$upscope $end
$enddefinitions $end
$comment Show the parameter values. $end
$dumpall
$end
#0
$dumpvars
b0 /
b0 .
b0 -
b0 ,
b0 +
b0 *
b0 )
b0 (
b0 '
b0 &
b0 %
b0 $
b0 #
b0 "
b0 !
$end
#15
b1 &
#25
b1 "
b1 ,
b1 !
b1 /
b1 $
b1 '
b1 *
b1 -
#30
b10 &
#40
b10 "
b10 ,
b10 !
b10 /
b10 $
b10 '
b10 *
b10 -
#45
b11 &
#55
b11 "
b11 ,
b11 !
b11 /
b11 $
b11 '
b11 *
b11 -
#60
b100 &
#70
b100 "
b100 ,
b100 !
b100 /
b100 $
b100 '
b100 *
b100 -
#75
b101 &
#85
b101 "
b101 ,
b101 !
b101 /
b101 $
b101 '
b101 *
b101 -
#90
b110 &
#100
b110 "
b110 ,
b110 !
b110 /
b110 $
b110 '
b110 *
b110 -
#105
b111 &
#115
b111 "
b111 ,
b111 !
b111 /
b111 $
b111 '
b111 *
b111 -
#120
b1000 &
#130
b1000 "
b1000 ,
b1000 !
b1000 /
b1000 $
b1000 '
b1000 *
b1000 -
#135
b1001 &
#145
b1001 "
b1001 ,
b1001 !
b1001 /
b1001 $
b1001 '
b1001 *
b1001 -
#150
b1010 &
#160
b1010 "
b1010 ,
b1010 !
b1010 /
b1010 $
b1010 '
b1010 *
b1010 -
#165
b1011 &
#175
b1011 "
b1011 ,
b1011 !
b1011 /
b1011 $
b1011 '
b1011 *
b1011 -
#180
b1100 &
#190
b1100 "
b1100 ,
b1100 !
b1100 /
b1100 $
b1100 '
b1100 *
b1100 -
#195
b1101 &
#205
b1101 "
b1101 ,
b1101 !
b1101 /
b1101 $
b1101 '
b1101 *
b1101 -
#210
b1110 &
#220
b1110 "
b1110 ,
b1110 !
b1110 /
b1110 $
b1110 '
b1110 *
b1110 -
#225
b1111 &
#235
b1111 "
b1111 ,
b1111 !
b1111 /
b1111 $
b1111 '
b1111 *
b1111 -
#240
b10000 &
#250
b1 "
b1 ,
b1 !
b1 /
b1 %
b1 (
b1 +
b1 .
b0 $
b0 '
b0 *
b0 -
#255
b10001 &
#265
b1 #
b1 )
b0 !
b0 /
b1 $
b1 '
b1 *
b1 -
#270
b10010 &
#280
b0 #
b0 )
b11 "
b11 ,
b11 !
b11 /
b10 $
b10 '
b10 *
b10 -
#285
b10011 &
#295
b1 #
b1 )
b10 !
b10 /
b11 $
b11 '
b11 *
b11 -
#300
b10100 &
#310
b0 #
b0 )
b101 "
b101 ,
b101 !
b101 /
b100 $
b100 '
b100 *
b100 -
#315
b10101 &
#325
b1 #
b1 )
b100 !
b100 /
b101 $
b101 '
b101 *
b101 -
#330
b10110 &
#340
b0 #
b0 )
b111 "
b111 ,
b111 !
b111 /
b110 $
b110 '
b110 *
b110 -
#345
b10111 &
#355
b1 #
b1 )
b110 !
b110 /
b111 $
b111 '
b111 *
b111 -
#360
b11000 &
#370
b0 #
b0 )
b1001 "
b1001 ,
b1001 !
b1001 /
b1000 $
b1000 '
b1000 *
b1000 -
#375
b11001 &
#385
b1 #
b1 )
b1000 !
b1000 /
b1001 $
b1001 '
b1001 *
b1001 -
#390
b11010 &
#400
b0 #
b0 )
b1011 "
b1011 ,
b1011 !
b1011 /
b1010 $
b1010 '
b1010 *
b1010 -
#405
b11011 &
#415
b1 #
b1 )
b1010 !
b1010 /
b1011 $
b1011 '
b1011 *
b1011 -
#420
b11100 &
#430
b0 #
b0 )
b1101 "
b1101 ,
b1101 !
b1101 /
b1100 $
b1100 '
b1100 *
b1100 -
#435
b11101 &
#445
b1 #
b1 )
b1100 !
b1100 /
b1101 $
b1101 '
b1101 *
b1101 -
#450
b11110 &
#460
b0 #
b0 )
b1111 "
b1111 ,
b1111 !
b1111 /
b1110 $
b1110 '
b1110 *
b1110 -
#465
b11111 &
#475
b1 #
b1 )
b1110 !
b1110 /
b1111 $
b1111 '
b1111 *
b1111 -
#480
b100000 &
#490
b0 #
b0 )
b10 "
b10 ,
b10 !
b10 /
b10 %
b10 (
b10 +
b10 .
b0 $
b0 '
b0 *
b0 -
#495
b100001 &
#505
b11 "
b11 ,
b11 !
b11 /
b1 $
b1 '
b1 *
b1 -
#510
b100010 &
#520
b10 #
b10 )
b10 "
b10 ,
b0 !
b0 /
b10 $
b10 '
b10 *
b10 -
#525
b100011 &
#535
b11 "
b11 ,
b1 !
b1 /
b11 $
b11 '
b11 *
b11 -
#540
b100100 &
#550
b0 #
b0 )
b110 "
b110 ,
b110 !
b110 /
b100 $
b100 '
b100 *
b100 -
#555
b100101 &
#565
b111 "
b111 ,
b111 !
b111 /
b101 $
b101 '
b101 *
b101 -
#570
b100110 &
#580
b10 #
b10 )
b110 "
b110 ,
b100 !
b100 /
b110 $
b110 '
b110 *
b110 -
#585
b100111 &
#595
b111 "
b111 ,
b101 !
b101 /
b111 $
b111 '
b111 *
b111 -
#600
b101000 &
#610
b0 #
b0 )
b1010 "
b1010 ,
b1010 !
b1010 /
b1000 $
b1000 '
b1000 *
b1000 -
#615
b101001 &
#625
b1011 "
b1011 ,
b1011 !
b1011 /
b1001 $
b1001 '
b1001 *
b1001 -
#630
b101010 &
#640
b10 #
b10 )
b1010 "
b1010 ,
b1000 !
b1000 /
b1010 $
b1010 '
b1010 *
b1010 -
#645
b101011 &
#655
b1011 "
b1011 ,
b1001 !
b1001 /
b1011 $
b1011 '
b1011 *
b1011 -
#660
b101100 &
#670
b0 #
b0 )
b1110 "
b1110 ,
b1110 !
b1110 /
b1100 $
b1100 '
b1100 *
b1100 -
#675
b101101 &
#685
b1111 "
b1111 ,
b1111 !
b1111 /
b1101 $
b1101 '
b1101 *
b1101 -
#690
b101110 &
#700
b10 #
b10 )
b1110 "
b1110 ,
b1100 !
b1100 /
b1110 $
b1110 '
b1110 *
b1110 -
#705
b101111 &
#715
b1111 "
b1111 ,
b1101 !
b1101 /
b1111 $
b1111 '
b1111 *
b1111 -
#720
b110000 &
#730
b0 #
b0 )
b11 "
b11 ,
b11 !
b11 /
b11 %
b11 (
b11 +
b11 .
b0 $
b0 '
b0 *
b0 -
#735
b110001 &
#745
b1 #
b1 )
b10 !
b10 /
b1 $
b1 '
b1 *
b1 -
#750
b110010 &
#760
b10 #
b10 )
b1 !
b1 /
b10 $
b10 '
b10 *
b10 -
#765
b110011 &
#775
b11 #
b11 )
b0 !
b0 /
b11 $
b11 '
b11 *
b11 -
#780
b110100 &
#790
b0 #
b0 )
b111 "
b111 ,
b111 !
b111 /
b100 $
b100 '
b100 *
b100 -
#795
b110101 &
#805
b1 #
b1 )
b110 !
b110 /
b101 $
b101 '
b101 *
b101 -
#810
b110110 &
#820
b10 #
b10 )
b101 !
b101 /
b110 $
b110 '
b110 *
b110 -
#825
b110111 &
#835
b11 #
b11 )
b100 !
b100 /
b111 $
b111 '
b111 *
b111 -
#840
b111000 &
#850
b0 #
b0 )
b1011 "
b1011 ,
b1011 !
b1011 /
b1000 $
b1000 '
b1000 *
b1000 -
#855
b111001 &
#865
b1 #
b1 )
b1010 !
b1010 /
b1001 $
b1001 '
b1001 *
b1001 -
#870
b111010 &
#880
b10 #
b10 )
b1001 !
b1001 /
b1010 $
b1010 '
b1010 *
b1010 -
#885
b111011 &
#895
b11 #
b11 )
b1000 !
b1000 /
b1011 $
b1011 '
b1011 *
b1011 -
#900
b111100 &
#910
b0 #
b0 )
b1111 "
b1111 ,
b1111 !
b1111 /
b1100 $
b1100 '
b1100 *
b1100 -
#915
b111101 &
#925
b1 #
b1 )
b1110 !
b1110 /
b1101 $
b1101 '
b1101 *
b1101 -
#930
b111110 &
#940
b10 #
b10 )
b1101 !
b1101 /
b1110 $
b1110 '
b1110 *
b1110 -
#945
b111111 &
#955
b11 #
b11 )
b1100 !
b1100 /
b1111 $
b1111 '
b1111 *
b1111 -
#960
b1000000 &
#970
b0 #
b0 )
b100 "
b100 ,
b100 !
b100 /
b100 %
b100 (
b100 +
b100 .
b0 $
b0 '
b0 *
b0 -
#975
b1000001 &
#985
b101 "
b101 ,
b101 !
b101 /
b1 $
b1 '
b1 *
b1 -
#990
b1000010 &
#1000
b110 "
b110 ,
b110 !
b110 /
b10 $
b10 '
b10 *
b10 -
#1005
b1000011 &
#1015
b111 "
b111 ,
b111 !
b111 /
b11 $
b11 '
b11 *
b11 -
#1020
b1000100 &
#1030
b100 #
b100 )
b100 "
b100 ,
b0 !
b0 /
b100 $
b100 '
b100 *
b100 -
#1035
b1000101 &
#1045
b101 "
b101 ,
b1 !
b1 /
b101 $
b101 '
b101 *
b101 -
#1050
b1000110 &
#1060
b110 "
b110 ,
b10 !
b10 /
b110 $
b110 '
b110 *
b110 -
#1065
b1000111 &
#1075
b111 "
b111 ,
b11 !
b11 /
b111 $
b111 '
b111 *
b111 -
#1080
b1001000 &
#1090
b0 #
b0 )
b1100 "
b1100 ,
b1100 !
b1100 /
b1000 $
b1000 '
b1000 *
b1000 -
#1095
b1001001 &
#1105
b1101 "
b1101 ,
b1101 !
b1101 /
b1001 $
b1001 '
b1001 *
b1001 -
#1110
b1001010 &
#1120
b1110 "
b1110 ,
b1110 !
b1110 /
b1010 $
b1010 '
b1010 *
b1010 -
#1125
b1001011 &
#1135
b1111 "
b1111 ,
b1111 !
b1111 /
b1011 $
b1011 '
b1011 *
b1011 -
#1140
b1001100 &
#1150
b100 #
b100 )
b1100 "
b1100 ,
b1000 !
b1000 /
b1100 $
b1100 '
b1100 *
b1100 -
#1155
b1001101 &
#1165
b1101 "
b1101 ,
b1001 !
b1001 /
b1101 $
b1101 '
b1101 *
b1101 -
#1170
b1001110 &
#1180
b1110 "
b1110 ,
b1010 !
b1010 /
b1110 $
b1110 '
b1110 *
b1110 -
#1185
b1001111 &
#1195
b1111 "
b1111 ,
b1011 !
b1011 /
b1111 $
b1111 '
b1111 *
b1111 -
#1200
b1010000 &
#1210
b0 #
b0 )
b101 "
b101 ,
b101 !
b101 /
b101 %
b101 (
b101 +
b101 .
b0 $
b0 '
b0 *
b0 -
#1215
b1010001 &
#1225
b1 #
b1 )
b100 !
b100 /
b1 $
b1 '
b1 *
b1 -
#1230
b1010010 &
#1240
b0 #
b0 )
b111 "
b111 ,
b111 !
b111 /
b10 $
b10 '
b10 *
b10 -
#1245
b1010011 &
#1255
b1 #
b1 )
b110 !
b110 /
b11 $
b11 '
b11 *
b11 -
#1260
b1010100 &
#1270
b100 #
b100 )
b101 "
b101 ,
b1 !
b1 /
b100 $
b100 '
b100 *
b100 -
#1275
b1010101 &
#1285
b101 #
b101 )
b0 !
b0 /
b101 $
b101 '
b101 *
b101 -
#1290
b1010110 &
#1300
b100 #
b100 )
b111 "
b111 ,
b11 !
b11 /
b110 $
b110 '
b110 *
b110 -
#1305
b1010111 &
#1315
b101 #
b101 )
b10 !
b10 /
b111 $
b111 '
b111 *
b111 -
#1320
b1011000 &
#1330
b0 #
b0 )
b1101 "
b1101 ,
b1101 !
b1101 /
b1000 $
b1000 '
b1000 *
b1000 -
#1335
b1011001 &
#1345
b1 #
b1 )
b1100 !
b1100 /
b1001 $
b1001 '
b1001 *
b1001 -
#1350
b1011010 &
#1360
b0 #
b0 )
b1111 "
b1111 ,
b1111 !
b1111 /
b1010 $
b1010 '
b1010 *
b1010 -
#1365
b1011011 &
#1375
b1 #
b1 )
b1110 !
b1110 /
b1011 $
b1011 '
b1011 *
b1011 -
#1380
b1011100 &
#1390
b100 #
b100 )
b1101 "
b1101 ,
b1001 !
b1001 /
b1100 $
b1100 '
b1100 *
b1100 -
#1395
b1011101 &
#1405
b101 #
b101 )
b1000 !
b1000 /
b1101 $
b1101 '
b1101 *
b1101 -
#1410
b1011110 &
#1420
b100 #
b100 )
b1111 "
b1111 ,
b1011 !
b1011 /
b1110 $
b1110 '
b1110 *
b1110 -
#1425
b1011111 &
#1435
b101 #
b101 )
b1010 !
b1010 /
b1111 $
b1111 '
b1111 *
b1111 -
#1440
b1100000 &
#1450
b0 #
b0 )
b110 "
b110 ,
b110 !
b110 /
b110 %
b110 (
b110 +
b110 .
b0 $
b0 '
b0 *
b0 -
#1455
b1100001 &
#1465
b111 "
b111 ,
b111 !
b111 /
b1 $
b1 '
b1 *
b1 -
#1470
b1100010 &
#1480
b10 #
b10 )
b110 "
b110 ,
b100 !
b100 /
b10 $
b10 '
b10 *
b10 -
#1485
b1100011 &
#1495
b111 "
b111 ,
b101 !
b101 /
b11 $
b11 '
b11 *
b11 -
#1500
b1100100 &
#1510
b100 #
b100 )
b110 "
b110 ,
b10 !
b10 /
b100 $
b100 '
b100 *
b100 -
#1515
b1100101 &
#1525
b111 "
b111 ,
b11 !
b11 /
b101 $
b101 '
b101 *
b101 -
#1530
b1100110 &
#1540
b110 #
b110 )
b110 "
b110 ,
b0 !
b0 /
b110 $
b110 '
b110 *
b110 -
#1545
b1100111 &
#1555
b111 "
b111 ,
b1 !
b1 /
b111 $
b111 '
b111 *
b111 -
#1560
b1101000 &
#1570
b0 #
b0 )
b1110 "
b1110 ,
b1110 !
b1110 /
b1000 $
b1000 '
b1000 *
b1000 -
#1575
b1101001 &
#1585
b1111 "
b1111 ,
b1111 !
b1111 /
b1001 $
b1001 '
b1001 *
b1001 -
#1590
b1101010 &
#1600
b10 #
b10 )
b1110 "
b1110 ,
b1100 !
b1100 /
b1010 $
b1010 '
b1010 *
b1010 -
#1605
b1101011 &
#1615
b1111 "
b1111 ,
b1101 !
b1101 /
b1011 $
b1011 '
b1011 *
b1011 -
#1620
b1101100 &
#1630
b100 #
b100 )
b1110 "
b1110 ,
b1010 !
b1010 /
b1100 $
b1100 '
b1100 *
b1100 -
#1635
b1101101 &
#1645
b1111 "
b1111 ,
b1011 !
b1011 /
b1101 $
b1101 '
b1101 *
b1101 -
#1650
b1101110 &
#1660
b110 #
b110 )
b1110 "
b1110 ,
b1000 !
b1000 /
b1110 $
b1110 '
b1110 *
b1110 -
#1665
b1101111 &
#1675
b1111 "
b1111 ,
b1001 !
b1001 /
b1111 $
b1111 '
b1111 *
b1111 -
#1680
b1110000 &
#1690
b0 #
b0 )
b111 "
b111 ,
b111 !
b111 /
b111 %
b111 (
b111 +
b111 .
b0 $
b0 '
b0 *
b0 -
#1695
b1110001 &
#1705
b1 #
b1 )
b110 !
b110 /
b1 $
b1 '
b1 *
b1 -
#1710
b1110010 &
#1720
b10 #
b10 )
b101 !
b101 /
b10 $
b10 '
b10 *
b10 -
#1725
b1110011 &
#1735
b11 #
b11 )
b100 !
b100 /
b11 $
b11 '
b11 *
b11 -
#1740
b1110100 &
#1750
b100 #
b100 )
b11 !
b11 /
b100 $
b100 '
b100 *
b100 -
#1755
b1110101 &
#1765
b101 #
b101 )
b10 !
b10 /
b101 $
b101 '
b101 *
b101 -
#1770
b1110110 &
#1780
b110 #
b110 )
b1 !
b1 /
b110 $
b110 '
b110 *
b110 -
#1785
b1110111 &
#1795
b111 #
b111 )
b0 !
b0 /
b111 $
b111 '
b111 *
b111 -
#1800
b1111000 &
#1810
b0 #
b0 )
b1111 "
b1111 ,
b1111 !
b1111 /
b1000 $
b1000 '
b1000 *
b1000 -
#1815
b1111001 &
#1825
b1 #
b1 )
b1110 !
b1110 /
b1001 $
b1001 '
b1001 *
b1001 -
#1830
b1111010 &
#1840
b10 #
b10 )
b1101 !
b1101 /
b1010 $
b1010 '
b1010 *
b1010 -
#1845
b1111011 &
#1855
b11 #
b11 )
b1100 !
b1100 /
b1011 $
b1011 '
b1011 *
b1011 -
#1860
b1111100 &
#1870
b100 #
b100 )
b1011 !
b1011 /
b1100 $
b1100 '
b1100 *
b1100 -
#1875
b1111101 &
#1885
b101 #
b101 )
b1010 !
b1010 /
b1101 $
b1101 '
b1101 *
b1101 -
#1890
b1111110 &
#1900
b110 #
b110 )
b1001 !
b1001 /
b1110 $
b1110 '
b1110 *
b1110 -
#1905
b1111111 &
#1915
b111 #
b111 )
b1000 !
b1000 /
b1111 $
b1111 '
b1111 *
b1111 -
#1920
b10000000 &
#1930
b0 #
b0 )
b1000 "
b1000 ,
b1000 %
b1000 (
b1000 +
b1000 .
b0 $
b0 '
b0 *
b0 -
#1935
b10000001 &
#1945
b1001 "
b1001 ,
b1001 !
b1001 /
b1 $
b1 '
b1 *
b1 -
#1950
b10000010 &
#1960
b1010 "
b1010 ,
b1010 !
b1010 /
b10 $
b10 '
b10 *
b10 -
#1965
b10000011 &
#1975
b1011 "
b1011 ,
b1011 !
b1011 /
b11 $
b11 '
b11 *
b11 -
#1980
b10000100 &
#1990
b1100 "
b1100 ,
b1100 !
b1100 /
b100 $
b100 '
b100 *
b100 -
#1995
b10000101 &
#2005
b1101 "
b1101 ,
b1101 !
b1101 /
b101 $
b101 '
b101 *
b101 -
#2010
b10000110 &
#2020
b1110 "
b1110 ,
b1110 !
b1110 /
b110 $
b110 '
b110 *
b110 -
#2025
b10000111 &
#2035
b1111 "
b1111 ,
b1111 !
b1111 /
b111 $
b111 '
b111 *
b111 -
#2040
b10001000 &
#2050
b1000 #
b1000 )
b1000 "
b1000 ,
b0 !
b0 /
b1000 $
b1000 '
b1000 *
b1000 -
#2055
b10001001 &
#2065
b1001 "
b1001 ,
b1 !
b1 /
b1001 $
b1001 '
b1001 *
b1001 -
#2070
b10001010 &
#2080
b1010 "
b1010 ,
b10 !
b10 /
b1010 $
b1010 '
b1010 *
b1010 -
#2085
b10001011 &
#2095
b1011 "
b1011 ,
b11 !
b11 /
b1011 $
b1011 '
b1011 *
b1011 -
#2100
b10001100 &
#2110
b1100 "
b1100 ,
b100 !
b100 /
b1100 $
b1100 '
b1100 *
b1100 -
#2115
b10001101 &
#2125
b1101 "
b1101 ,
b101 !
b101 /
b1101 $
b1101 '
b1101 *
b1101 -
#2130
b10001110 &
#2140
b1110 "
b1110 ,
b110 !
b110 /
b1110 $
b1110 '
b1110 *
b1110 -
#2145
b10001111 &
#2155
b1111 "
b1111 ,
b111 !
b111 /
b1111 $
b1111 '
b1111 *
b1111 -
#2160
b10010000 &
#2170
b0 #
b0 )
b1001 "
b1001 ,
b1001 !
b1001 /
b1001 %
b1001 (
b1001 +
b1001 .
b0 $
b0 '
b0 *
b0 -
#2175
b10010001 &
#2185
b1 #
b1 )
b1000 !
b1000 /
b1 $
b1 '
b1 *
b1 -
#2190
b10010010 &
#2200
b0 #
b0 )
b1011 "
b1011 ,
b1011 !
b1011 /
b10 $
b10 '
b10 *
b10 -
#2205
b10010011 &
#2215
b1 #
b1 )
b1010 !
b1010 /
b11 $
b11 '
b11 *
b11 -
#2220
b10010100 &
#2230
b0 #
b0 )
b1101 "
b1101 ,
b1101 !
b1101 /
b100 $
b100 '
b100 *
b100 -
#2235
b10010101 &
#2245
b1 #
b1 )
b1100 !
b1100 /
b101 $
b101 '
b101 *
b101 -
#2250
b10010110 &
#2260
b0 #
b0 )
b1111 "
b1111 ,
b1111 !
b1111 /
b110 $
b110 '
b110 *
b110 -
#2265
b10010111 &
#2275
b1 #
b1 )
b1110 !
b1110 /
b111 $
b111 '
b111 *
b111 -
#2280
b10011000 &
#2290
b1000 #
b1000 )
b1001 "
b1001 ,
b1 !
b1 /
b1000 $
b1000 '
b1000 *
b1000 -
#2295
b10011001 &
#2305
b1001 #
b1001 )
b0 !
b0 /
b1001 $
b1001 '
b1001 *
b1001 -
#2310
b10011010 &
#2320
b1000 #
b1000 )
b1011 "
b1011 ,
b11 !
b11 /
b1010 $
b1010 '
b1010 *
b1010 -
#2325
b10011011 &
#2335
b1001 #
b1001 )
b10 !
b10 /
b1011 $
b1011 '
b1011 *
b1011 -
#2340
b10011100 &
#2350
b1000 #
b1000 )
b1101 "
b1101 ,
b101 !
b101 /
b1100 $
b1100 '
b1100 *
b1100 -
#2355
b10011101 &
#2365
b1001 #
b1001 )
b100 !
b100 /
b1101 $
b1101 '
b1101 *
b1101 -
#2370
b10011110 &
#2380
b1000 #
b1000 )
b1111 "
b1111 ,
b111 !
b111 /
b1110 $
b1110 '
b1110 *
b1110 -
#2385
b10011111 &
#2395
b1001 #
b1001 )
b110 !
b110 /
b1111 $
b1111 '
b1111 *
b1111 -
#2400
b10100000 &
#2410
b0 #
b0 )
b1010 "
b1010 ,
b1010 !
b1010 /
b1010 %
b1010 (
b1010 +
b1010 .
b0 $
b0 '
b0 *
b0 -
#2415
b10100001 &
#2425
b1011 "
b1011 ,
b1011 !
b1011 /
b1 $
b1 '
b1 *
b1 -
#2430
b10100010 &
#2440
b10 #
b10 )
b1010 "
b1010 ,
b1000 !
b1000 /
b10 $
b10 '
b10 *
b10 -
#2445
b10100011 &
