Aeolus/src/ALU.v
// Arithmetic Logic Unit

// Arithmetic Unit Components
/*
         Arithmetic Unit
              \
            8-bit RC Adder
                 \
                4-Bit Adder
                    \     
                Full adder 
*/


module ArithmeticUnit (
    input wire       clk,
    input wire       reset,
    input            add,
    input            sub,
    input            lshift,
    input            rshift,
    input wire [3:0] in1,
    input wire [3:0] in2, 
    output reg [3:0] out,
    output reg       overflow

);

    wire [3:0] shiftOut, adderOut, subtractorOut;
    wire shiftFlag, adderOverflowFlag, subtractorOverflowFlag;

    ShiftRegister       sr         (clk, in1, enable, {lshift,rshift}, shiftOut, shiftFlag);
    CombAdder_4bit      adder      (in1, in2, adderOut, adderOverflowFlag);
    CombSubtractor_4bit subtractor (in1, in2, subtractorOut, subtractorOverflowFlag);

    always @(posedge clk) begin // assumes control signals can't be sent together
        
        if (add) begin
            out <= adderOut;
            overflow <= adderOverflowFlag;
        end

        if (sub) begin
            out <= subtractorOut;
            overflow <= subtractorOverflowFlag;
        end

        if (lshift || rshift)
            out <= shiftOut;
            overflow <= shiftFlag;
    end



endmodule


module ShiftRegister(  // sequential shift register (D type FF with Enable)
        input wire       clk,
        input wire [3:0] in,
        input wire       loadEnable,
        input      [1:0] shiftstate,  //reg
        output reg [3:0] out,
        output reg       flag
);
    
    reg [3:0] inReg  = 0;

    always @(posedge clk) begin
        if (loadEnable) begin
            inReg <= in;    
        end

        if (shiftstate == 2'b10) begin     // LSH
             {flag,out} = inReg << 1;

        end if (shiftstate == 2'b01) begin // RSH
            {flag,out} = inReg >> 1;
        end

    end

endmodule

module FullAdder(
    input wire in1,
    input wire in2,
    input wire carryIn,
    output  sum,
    output  carryOut
);
    assign {carryOut,sum} = in1 + in2; // behavioural description

endmodule

// ripple carry adder 4-bits - not verified
module SyncRippleCarryAdder_4bit ( // synchronous design, hierarchal desgin
    input wire         clk,
    input wire         reset,
    input wire  [3:0]  in1,
    input wire  [3:0]  in2,
    output reg  [3:0]  out,
    output reg         overflow
);
    wire carry1,carry2,carry3,carry4;
    reg c1, c2, c3;

    wire o0, o1, o2, o3;

    FullAdder f1 (in1[0], in2[0], 1'b0, o0, carry1);
    FullAdder f2 (in1[1], in2[1], c1,   o1, carry2);
    FullAdder f3 (in1[2], in2[2], c2,   o2, carry3);
    FullAdder f4 (in1[3], in2[3], c3,   o3, carry4);

    always @(posedge clk) begin
        if (~reset) begin
            c1 <= carry1;
            c2 <= carry2;
            c3 <= carry3;

            out[0] <= o0;
            out[1] <= o1;
            out[2] <= o2;
            out[3] <= o3;
            overflow <= carry4;
        
        end else begin
            c1 <= 0;
            c2 <= 0;
            c3 <= 0;

            out[0] <= 0;
            out[1] <= 0;
            out[2] <= 0;
            out[3] <= 0;
            overflow <= 0;
        end

    end

endmodule

// 4-bit adder
module CombAdder_4bit ( // Conbinational, Behavioural Description
    input wire  [3:0]  in1,
    input wire  [3:0]  in2,
    output reg  [3:0]  out,
    output reg         overflow  
);

    always @(*) begin
        {overflow, out} <= in1 + in2;
    end

endmodule

//  4-bit Subtractor
module CombSubtractor_4bit (  // Combinational - Behavioural Description
    input wire  [3:0]  in1,
    input wire  [3:0]  in2,
    output reg  [3:0]  out,
    output reg         overflow  
);

    always @(*) begin
        {overflow, out} <= in1 - in2;
    end

endmodule

// 4-bit Adder
module SyncAdder_4bit (  // Synchronous, Behavioural Descriptiion
    input wire         clk,
    input wire         reset,
    input wire  [3:0]  in1,
    input wire  [3:0]  in2,
    output reg  [3:0]  out,
    output reg         overflow  // what does this represent in a subtractionn?
);
    always @(posedge clk) begin
        if (~reset) begin
            {overflow, out} <= in1 + in2;
        end begin
            out <= 0;
        end
    end 

endmodule

//4-bit Subtractor
module SyncSubtractor_4bit (  // Synchronous, Behavioural Descriptiion
    input wire         clk,
    input wire         reset,
    input wire  [3:0]  in1,
    input wire  [3:0]  in2,
    output reg  [3:0]  out,
    output reg         overflow  // what does this represent in a subtractionn?
);

    always @(posedge clk ) begin
        if (~reset) begin
            {overflow, out} <= in1 - in2;
        end begin
            out <= 0;
        end
    end 

endmodule

Aeolus/test/shifterTB.v

//Subtractor  Testbench

`timescale 1ns/1ns
`include "src/ALU.v"

//Assertion macro

`define assert(signal, value) if (signal !== value) begin  $display("ASSERTION FAILED in test %4b at time %0t ns : %m signal  !=  value expected: %5b, got: %5b", i[3:0], $time , value, signal); $finish; end

module ShifterTb();

    reg        CLK;
    reg        RESET;
    reg  [3:0] IN1;
    reg        LOAD_ENABLE;
    reg        LSH;
    reg        RSH;
    wire [3:0] OUT;
    wire       FLAG;
    
    integer i;

    ShiftRegister uut (CLK,IN1,LOAD_ENABLE, {LSH,RSH}, OUT, FLAG);

    initial begin

        $dumpfile("test/vcd/shifterdump.vcd");
        $dumpvars(0, ShifterTb);
        
        CLK = 0; IN1 = 0; LOAD_ENABLE = 0; LOAD_ENABLE = 0; LSH = 0; RSH = 0; 

        $display("4-Bit Shifter Test");

        //$display("   in1   |  in2     |  actual    |  expected");

        // Test LDS

        #10 LOAD_ENABLE = 1;
        $display("LDS TEST");
        for (i = 0; i < 16 ; i = i + 1) begin
            #5  {IN1} = i[3:0];
            #5  `assert({uut.inReg}, (i[3:0]));  // assert that the result is the shift
        end
        $display("Test Completed!");

     
        // Test LSH
        $display("LSH TEST");
        #10 LSH = 1; IN1 = 0;
        for (i = 0; i < 16 ; i = i + 1) begin
            #5 {IN1} = i[3:0];
            //#5  $display("  %4b    |   %4b  |   %4b   |   %5b   " ,IN1, IN2,  (i[3:0] + i[7:4]) , {OVERFLOW,OUT} );
            #15 `assert({FLAG,OUT}, (i[3:0] << 1 ));  // assert that the result is LSH after 1 cycle
        end
        $display("Test Completed!");

        // Test RSH
                
         $display("RSH TEST");
         #10 IN1 = 0;
         #10 LSH = 0; RSH = 1;

        for (i = 0; i < 16 ; i = i + 1) begin
            #5 {IN1} = i[3:0];
            //#5  $display("  %4b    |   %4b  |   %4b   |   %5b   " ,IN1, IN2,  (i[3:0] + i[7:4]) , {OVERFLOW,OUT} );
            #15 `assert({FLAG,OUT}, (i[3:0] >> 1));  // assert that the result is RSH after 1 cycle
        end
        

        $display("TEST SUCCESSFUL!"); $finish; 

    end

    always  begin
        #5 CLK = ~CLK;
    end

endmodule

Aeolus/test/vcd/shifterdump.vcd
$date
	Tue Feb 18 12:08:01 2025
$end
$version
	Icarus Verilog
$end
$timescale
	1ns
$end
$scope module ShifterTb $end
$var wire 4 ! OUT [3:0] $end
$var wire 1 " FLAG $end
$var reg 1 # CLK $end
$var reg 4 $ IN1 [3:0] $end
$var reg 1 % LOAD_ENABLE $end
$var reg 1 & LSH $end
$var reg 1 ' RSH $end
$var integer 32 ( i [31:0] $end
$scope module uut $end
$var wire 1 # clk $end
$var wire 4 ) in [3:0] $end
$var wire 1 % loadEnable $end
$var wire 2 * shiftstate [1:0] $end
$var reg 1 " flag $end
$var reg 4 + inReg [3:0] $end
$var reg 4 , out [3:0] $end
$upscope $end
$upscope $end
$enddefinitions $end
$comment Show the parameter values. $end
$dumpall
$end
#0
$dumpvars
bx ,
b0 +
b0 *
b0 )
bx (
0'
0&
0%
b0 $
0#
x"
bx !
$end
#5
1#
#10
0#
b0 (
1%
#15
1#
#20
0#
b1 (
#25
b1 +
1#
b1 $
b1 )
#30
0#
b10 (
#35
b10 +
1#
b10 $
b10 )
#40
0#
b11 (
#45
b11 +
1#
b11 $
b11 )
#50
0#
b100 (
#55
b100 +
1#
b100 $
b100 )
#60
0#
b101 (
#65
b101 +
1#
b101 $
b101 )
#70
0#
b110 (
#75
b110 +
1#
b110 $
b110 )
#80
0#
b111 (
#85
b111 +
1#
b111 $
b111 )
#90
0#
b1000 (
#95
b1000 +
1#
b1000 $
b1000 )
#100
0#
b1001 (
#105
b1001 +
1#
b1001 $
b1001 )
#110
0#
b1010 (
#115
b1010 +
1#
b1010 $
b1010 )
#120
0#
b1011 (
#125
b1011 +
1#
b1011 $
b1011 )
#130
0#
b1100 (
#135
b1100 +
1#
b1100 $
b1100 )
#140
0#
b1101 (
#145
b1101 +
1#
b1101 $
b1101 )
#150
0#
b1110 (
#155
b1110 +
1#
b1110 $
b1110 )
#160
0#
b1111 (
#165
b1111 +
1#
b1111 $
b1111 )
#170
0#
b10000 (
#175
1#
#180
0#
b0 (
b0 $
b0 )
b10 *
1&
#185
b0 +
1"
b1110 !
b1110 ,
1#
#190
0#
#195
0"
b0 !
b0 ,
1#
#200
0#
b1 (
#205
b1 +
1#
b1 $
b1 )
#210
0#
#215
b10 !
b10 ,
1#
#220
0#
b10 (
#225
b10 +
1#
b10 $
b10 )
#230
0#
#235
b100 !
b100 ,
1#
#240
0#
b11 (
#245
b11 +
1#
b11 $
b11 )
#250
0#
#255
b110 !
b110 ,
1#
#260
0#
b100 (
#265
b100 +
1#
b100 $
b100 )
#270
0#
#275
b1000 !
b1000 ,
1#
#280
0#
b101 (
#285
b101 +
1#
b101 $
b101 )
#290
0#
#295
b1010 !
b1010 ,
1#
#300
0#
b110 (
#305
b110 +
1#
b110 $
b110 )
#310
0#
#315
b1100 !
b1100 ,
1#
#320
0#
b111 (
#325
b111 +
1#
b111 $
b111 )
#330
0#
#335
b1110 !
b1110 ,
1#
#340
0#
b1000 (
#345
b1000 +
1#
b1000 $
b1000 )
#350
0#
#355
1"
b0 !
b0 ,
1#
#360
0#
b1001 (
#365
b1001 +
1#
b1001 $
b1001 )
#370
0#
#375
b10 !
b10 ,
1#
#380
0#
b1010 (
#385
b1010 +
1#
b1010 $
b1010 )
#390
0#
#395
b100 !
b100 ,
1#
#400
0#
b1011 (
#405
b1011 +
1#
b1011 $
b1011 )
#410
0#
#415
b110 !
b110 ,
1#
#420
0#
b1100 (
#425
b1100 +
1#
b1100 $
b1100 )
#430
0#
#435
b1000 !
b1000 ,
1#
#440
0#
b1101 (
#445
b1101 +
1#
b1101 $
b1101 )
#450
0#
#455
b1010 !
b1010 ,
1#
#460
0#
b1110 (
#465
b1110 +
1#
b1110 $
b1110 )
#470
0#
#475
b1100 !
b1100 ,
1#
#480
0#
b1111 (
#485
b1111 +
1#
b1111 $
b1111 )
#490
0#
#495
b1110 !
b1110 ,
1#
#500
0#
b10000 (
#505
1#
#510
0#
b0 $
b0 )
#515
b0 +
1#
#520
0#
b0 (
1'
b1 *
0&
#525
0"
b0 !
b0 ,
1#
#530
0#
#535
1#
#540
0#
b1 (
#545
b1 +
1#
b1 $
b1 )
#550
0#
#555
1#
#560
0#
b10 (
#565
b10 +
1#
b10 $
b10 )
#570
0#
#575
b1 !
b1 ,
1#
#580
0#
b11 (
#585
b11 +
1#
b11 $
b11 )
#590
0#
#595
1#
#600
0#
b100 (
#605
b100 +
1#
b100 $
b100 )
#610
0#
#615
b10 !
b10 ,
1#
#620
0#
b101 (
#625
b101 +
1#
b101 $
b101 )
#630
0#
#635
1#
#640
0#
b110 (
#645
b110 +
1#
b110 $
b110 )
#650
0#
#655
b11 !
b11 ,
1#
#660
0#
b111 (
#665
b111 +
1#
b111 $
b111 )
#670
0#
#675
1#
#680
0#
b1000 (
#685
b1000 +
1#
b1000 $
b1000 )
#690
0#
#695
b100 !
b100 ,
1#
#700
0#
b1001 (
#705
b1001 +
1#
b1001 $
b1001 )
#710
0#
#715
1#
#720
0#
b1010 (
#725
b1010 +
1#
b1010 $
b1010 )
#730
0#
#735
b101 !
b101 ,
1#
#740
0#
b1011 (
#745
b1011 +
1#
b1011 $
b1011 )
#750
0#
#755
1#
#760
0#
b1100 (
#765
b1100 +
1#
b1100 $
b1100 )
#770
0#
#775
b110 !
b110 ,
1#
#780
0#
b1101 (
#785
b1101 +
1#
b1101 $
b1101 )
#790
0#
#795
1#
#800
0#
b1110 (
#805
b1110 +
1#
b1110 $
b1110 )
#810
0#
#815
b111 !
b111 ,
1#
#820
0#
b1111 (
#825
b1111 +
1#
b1111 $
b1111 )
#830
0#
#835
1#
#840
0#
b10000 (
