Aeolus/src/Registers.v
// Registers

module DFF_4bit ( //DFF used just for buffering signals
    input wire clk,
    input wire [3:0] D,
    output reg [3:0] Q
);

    always @(posedge clk) begin
            Q <= D;
    end

endmodule

module DFF ( //DFF used just for buffering signals
    input wire clk,
    input wire  D,
    output reg  Q
);

    always @(posedge clk) begin
            Q <= D;
    end

endmodule

module EnableDFF_4bit(
    input wire clk,
    input wire enable,
    input wire [3:0] D,
    output reg [3:0] Q
);

    always @(posedge clk) begin
        if (enable) begin
            Q <= D;
        end
    end

endmodule

module ResetEnableDFF_4bit( // synchronous reset
    input wire clk,
    input wire reset,
    input wire enable,
    input wire [3:0] D,
    output reg [3:0] Q
);

    always @(posedge clk) begin
        if (~reset) begin
            if (enable) begin
                Q <= D;
            end 
        end else begin // reset behaviour
            Q <= 0;
        end
    end

endmodule

module ResetDFF_4bit ( // synchronous reset, no enable
    input wire clk,
    input wire reset,
    input wire [3:0] D,
    output reg [3:0] Q
);

    always @(posedge clk) begin
        if (~reset) begin
            Q <= D;
        end else begin // reset behaviour
            Q <= 0;
        end
    end

endmodule

Aeolus/src/ALU.v
// Arithmetic Logic Unit

`include "src/Registers.v"

// Arithmetic Unit Components
/*
               Arithmetic Unit
            /         |         \
        4bitAdder 4bitSubtractor 4bitShifter
        
*/

module ArithmeticLogicUnit (
    input wire       clk,
    input wire       reset,
    input            ADD,
    input            SUB,
    input            LSR,
    input            LSH,
    input            RSH,
    input wire       AND,
    input wire       OR,
    input wire       XOR,
    input wire       INV,
    input wire       CLR,
    input wire [3:0] in1,
    input wire [3:0] in2, 
    output reg [3:0] out,
    output reg       overflow,
    output wire      shiftFlag

);

    wire [3:0] shiftOut, adderOut, subtractorOut;
    wire adderOverflowFlag, subtractorOverflowFlag;
    wire [3:0] andOut;
    wire [3:0] orOut;
    wire [3:0] xorOut;
    wire [3:0] notOut;

    ShiftRegister       sr         (clk, in1, LSR, {LSH,RSH}, shiftOut, shiftFlag);
    CombAdder_4bit      adder      (in1, in2, adderOut, adderOverflowFlag);
    CombSubtractor_4bit subtractor (in1, in2, subtractorOut, subtractorOverflowFlag);
    And_4bit            andGate    (in1, in2, andOut);
    Or_4bit             orGate     (in1, in2, orOut);
    Xor_4bit            xorGate    (in1, in2, xorOut);
    Inv_4bit            notGate    (in1, notOut);


    always @(*) begin // mux for control signals - assumes they won't be sent together
    
        // Arithmetic
        if (ADD) begin
            out = adderOut;
            overflow = adderOverflowFlag;
        end

        if (SUB) begin
            out = subtractorOut;
            overflow = subtractorOverflowFlag;
        end

        if (LSH) begin
            out = shiftOut;
        end

        if (RSH) begin
            out = shiftOut;
        end

        // Logic
        if (AND) begin
            out =  andOut;
            overflow = 0; 
        end

        if (OR) begin
            out =  orOut;
            overflow = 0;
        end

        if (XOR) begin
            out =  xorOut;
            overflow = 0;    
        end

        if (INV) begin
            out =  notOut;
            overflow = 0;    
        end

        if (CLR) begin
            out =  0;
            overflow = 0;    
        end
        
    end

endmodule


module ShiftRegister (  // sequential shift register (D type FF with Enable)
    input wire       clk,
    input wire [3:0] in,
    input wire       loadEnable,
    input      [1:0] shiftState,  //reg
    output reg [3:0] out,
    output reg       flag
);
   
    wire [3:0] dataReg;

    EnableDFF_4bit inShift (clk, loadEnable, in, dataReg); // sequential load

        always @(*) begin
            case (shiftState)    // combinatorial output  
                2: begin      // LSH
                    {flag,out} = dataReg << 1;
                end 
                1: begin // RSH
                    {flag,out} = dataReg >> 1;
                end
                default begin  
                    out = dataReg;
                end 
            endcase
        end 

endmodule

module FullAdder(
    input wire in1,
    input wire in2,
    input wire carryIn,
    output  sum,
    output  carryOut
);
    assign {carryOut,sum} = in1 + in2; // behavioural description

endmodule

// ripple carry adder 4-bits - not verified
module SyncRippleCarryAdder_4bit (  // synchronous design, hierarchal desgin
    input wire         clk,
    input wire         reset,
    input wire  [3:0]  in1,
    input wire  [3:0]  in2,
    output reg  [3:0]  out,
    output reg         overflow
);
    wire carry1,carry2,carry3,carry4;
    reg c1, c2, c3;

    wire o0, o1, o2, o3;

    FullAdder f1 (in1[0], in2[0], 1'b0, o0, carry1);
    FullAdder f2 (in1[1], in2[1], c1,   o1, carry2);
    FullAdder f3 (in1[2], in2[2], c2,   o2, carry3);
    FullAdder f4 (in1[3], in2[3], c3,   o3, carry4);

    always @(posedge clk) begin
        if (~reset) begin
            c1 <= carry1;
            c2 <= carry2;
            c3 <= carry3;

            out[0] <= o0;
            out[1] <= o1;
            out[2] <= o2;
            out[3] <= o3;
            overflow <= carry4;
        
        end else begin
            c1 <= 0;
            c2 <= 0;
            c3 <= 0;

            out[0] <= 0;
            out[1] <= 0;
            out[2] <= 0;
            out[3] <= 0;
            overflow <= 0;
        end

    end

endmodule

// 4-bit adder
module CombAdder_4bit ( // Conbinational, Behavioural Description
    input wire  [3:0]  in1,
    input wire  [3:0]  in2,
    output reg  [3:0]  out,
    output reg         overflow  
);

    always @(*) begin
        {overflow, out} = in1 + in2;
    end

endmodule

//  4-bit Subtractor
module CombSubtractor_4bit (  // Combinational - Behavioural Description
    input wire  [3:0]  in1,
    input wire  [3:0]  in2,
    output reg  [3:0]  out,
    output reg        overflow  
);

    always @(*) begin
        {overflow, out} = in1 - in2;
    end

endmodule

// 4-bit Adder
module SyncAdder_4bit (  // Synchronous, Behavioural Descriptiion
    input wire         clk,
    input wire         reset,
    input wire  [3:0]  in1,
    input wire  [3:0]  in2,
    output reg  [3:0]  out,
    output reg         overflow  // what does this represent in a subtractionn?
);
    always @(posedge clk) begin
        if (~reset) begin
            {overflow, out} = in1 + in2;
        end else begin
            out = 0;
        end
    end 

endmodule

//4-bit Subtractor
module SyncSubtractor_4bit (  // Synchronous, Behavioural Descriptiion
    input wire         clk,
    input wire         reset,
    input wire  [3:0]  in1,
    input wire  [3:0]  in2,
    output reg  [3:0]  out,
    output reg         overflow  // what does this represent in a subtractionn?
);

    always @(posedge clk ) begin
        if (~reset) begin
            {overflow, out} = in1 - in2;
        end else begin
            out = 0;
        end
    end 

endmodule

// Logic Unit Components

/*         Logic Unit
        /      |       \
      AND      OR       XOR 
*/


//4-bit AND - combinational
module And_4bit(
    input wire [3:0] in1,
    input wire [3:0] in2,
    output wire [3:0] out
);

    assign out = in1 & in2;

endmodule 

// 4-bit OR - combinational
module Or_4bit(
    input wire [3:0] in1,
    input wire [3:0] in2,
    output wire [3:0] out
);

    assign out = in1 | in2;

endmodule

//4 -bit XOR - combinational 
module Xor_4bit (
    input wire [3:0] in1, in2,
    output wire [3:0] out
);

    assign out = in1 ^ in2;

endmodule 

//4 -bit XOR - combinational 
module  Inv_4bit (
    input wire [3:0] in1, 
    output wire [3:0] out
);

    assign out = ~in1;

endmodule

Aeolus/test/shifterTB.v

//Subtractor  Testbench

`timescale 1ns/1ns
`include "src/ALU.v"

//Assertion macro

`define assert(signal, value) if (signal !== value) begin  $display("ASSERTION FAILED in test %4b at time %0t ns : %m signal  !=  value expected: %5b, got: %5b", i[3:0], $time , value, signal); $finish; end

module ShifterTb();

    reg        CLK;
    reg        RESET;
    reg  [3:0] IN1;
    reg        LOAD_ENABLE;
    reg        LSH;
    reg        RSH;
    wire [3:0] OUT;
    wire       FLAG;
    
    integer i;

    ShiftRegister uut (CLK,IN1,LOAD_ENABLE, {LSH,RSH}, OUT, FLAG);

    initial begin

        $dumpfile("test/vcd/shifterdump.vcd");
        $dumpvars(0, ShifterTb);
        
        CLK = 0; IN1 = 0; LOAD_ENABLE = 0; LOAD_ENABLE = 0; LSH = 0; RSH = 0; 

        $display("4-Bit Shifter Test");

        //$display("   in1   |  in2     |  actual    |  expected");

        // Test LDS

        #10 LOAD_ENABLE = 1;
        $display("LDS TEST");
        for (i = 0; i < 16 ; i = i + 1) begin
            #5  {IN1} = i[3:0];
            #5  `assert({uut.inReg}, (i[3:0]));  // assert that the result is the shift
        end
        $display("Test Completed!");

     
        // Test LSH
        $display("LSH TEST");
        #10 LSH = 1; IN1 = 0;
        for (i = 0; i < 16 ; i = i + 1) begin
            #5 {IN1} = i[3:0];
            //#5  $display("  %4b    |   %4b  |   %4b   |   %5b   " ,IN1, IN2,  (i[3:0] + i[7:4]) , {OVERFLOW,OUT} );
            #15 `assert({FLAG,OUT}, (i[3:0] << 1 ));  // assert that the result is LSH after 1 cycle
        end
        $display("Test Completed!");

        // Test RSH
                
         $display("RSH TEST");
         #10 IN1 = 0;
         #10 LSH = 0; RSH = 1;

        for (i = 0; i < 16 ; i = i + 1) begin
            #5 {IN1} = i[3:0];
            //#5  $display("  %4b    |   %4b  |   %4b   |   %5b   " ,IN1, IN2,  (i[3:0] + i[7:4]) , {OVERFLOW,OUT} );
            #15 `assert({FLAG,OUT}, (i[3:0] >> 1));  // assert that the result is RSH after 1 cycle
        end
        

        $display("TEST SUCCESSFUL!"); $finish; 

    end

    always  begin
        #5 CLK = ~CLK;
    end

endmodule

Aeolus/test/vcd/shifterdump.vcd
$date
	Fri Feb 21 15:44:59 2025
$end
$version
	Icarus Verilog
$end
$timescale
	1ns
$end
$scope module ShifterTb $end
$var wire 4 ! OUT [3:0] $end
$var wire 1 " FLAG $end
$var reg 1 # CLK $end
$var reg 4 $ IN1 [3:0] $end
$var reg 1 % LOAD_ENABLE $end
$var reg 1 & LSH $end
$var reg 1 ' RSH $end
$var integer 32 ( i [31:0] $end
$scope module uut $end
$var wire 1 # clk $end
$var wire 4 ) in [3:0] $end
$var wire 1 % loadEnable $end
$var wire 2 * shiftState [1:0] $end
$var wire 4 + dataReg [3:0] $end
$var reg 1 " flag $end
$var reg 4 , out [3:0] $end
$scope module inShift $end
$var wire 4 - D [3:0] $end
$var wire 1 # clk $end
$var wire 1 % enable $end
$var reg 4 . Q [3:0] $end
$upscope $end
$upscope $end
$upscope $end
$enddefinitions $end
$comment Show the parameter values. $end
$dumpall
$end
#0
$dumpvars
bx .
b0 -
bx ,
bx +
b0 *
b0 )
bx (
0'
0&
0%
b0 $
0#
x"
bx !
$end
#5
1#
#10
0#
b0 (
1%
#15
b0 !
b0 ,
b0 +
b0 .
1#
#20
0#
b1 (
#25
b1 !
b1 ,
b1 +
b1 .
1#
b1 $
b1 )
b1 -
#30
0#
b10 (
#35
b10 !
b10 ,
b10 +
b10 .
1#
b10 $
b10 )
b10 -
#40
0#
b11 (
#45
b11 !
b11 ,
b11 +
b11 .
1#
b11 $
b11 )
b11 -
#50
0#
b100 (
#55
b100 !
b100 ,
b100 +
b100 .
1#
b100 $
b100 )
b100 -
#60
0#
b101 (
#65
b101 !
b101 ,
b101 +
b101 .
1#
b101 $
b101 )
b101 -
#70
0#
b110 (
#75
b110 !
b110 ,
b110 +
b110 .
1#
b110 $
b110 )
b110 -
#80
0#
b111 (
#85
b111 !
b111 ,
b111 +
b111 .
1#
b111 $
b111 )
b111 -
#90
0#
b1000 (
#95
b1000 !
b1000 ,
b1000 +
b1000 .
1#
b1000 $
b1000 )
b1000 -
#100
0#
b1001 (
#105
b1001 !
b1001 ,
b1001 +
b1001 .
1#
b1001 $
b1001 )
b1001 -
#110
0#
b1010 (
#115
b1010 !
b1010 ,
b1010 +
b1010 .
1#
b1010 $
b1010 )
b1010 -
#120
0#
b1011 (
#125
b1011 !
b1011 ,
b1011 +
b1011 .
1#
b1011 $
b1011 )
b1011 -
#130
0#
b1100 (
#135
b1100 !
b1100 ,
b1100 +
b1100 .
1#
b1100 $
b1100 )
b1100 -
#140
0#
b1101 (
#145
b1101 !
b1101 ,
b1101 +
b1101 .
1#
b1101 $
b1101 )
b1101 -
#150
0#
b1110 (
#155
b1110 !
b1110 ,
b1110 +
b1110 .
1#
b1110 $
b1110 )
b1110 -
#160
0#
b1111 (
#165
b1111 !
b1111 ,
b1111 +
b1111 .
1#
b1111 $
b1111 )
b1111 -
#170
0#
b10000 (
#175
1#
#180
1"
b1110 !
b1110 ,
0#
b0 (
b0 $
b0 )
b0 -
b10 *
1&
#185
0"
b0 !
b0 ,
b0 +
b0 .
1#
#190
0#
#195
1#
#200
0#
b1 (
#205
b10 !
b10 ,
b1 +
b1 .
1#
b1 $
b1 )
b1 -
#210
0#
#215
1#
#220
0#
b10 (
#225
b100 !
b100 ,
b10 +
b10 .
1#
b10 $
b10 )
b10 -
#230
0#
#235
1#
#240
0#
b11 (
#245
b110 !
b110 ,
b11 +
b11 .
1#
b11 $
b11 )
b11 -
#250
0#
#255
1#
#260
0#
b100 (
#265
b1000 !
b1000 ,
b100 +
b100 .
1#
b100 $
b100 )
b100 -
#270
0#
#275
1#
#280
0#
b101 (
#285
b1010 !
b1010 ,
b101 +
b101 .
1#
b101 $
b101 )
b101 -
#290
0#
#295
1#
#300
0#
b110 (
#305
b1100 !
b1100 ,
b110 +
b110 .
1#
b110 $
b110 )
b110 -
#310
0#
#315
1#
#320
0#
b111 (
#325
b1110 !
b1110 ,
b111 +
b111 .
1#
b111 $
b111 )
b111 -
#330
0#
#335
1#
#340
0#
b1000 (
#345
1"
b0 !
b0 ,
b1000 +
b1000 .
1#
b1000 $
b1000 )
b1000 -
#350
0#
#355
1#
#360
0#
b1001 (
#365
b10 !
b10 ,
b1001 +
b1001 .
1#
b1001 $
b1001 )
b1001 -
#370
0#
#375
1#
#380
0#
b1010 (
#385
b100 !
b100 ,
b1010 +
b1010 .
1#
b1010 $
b1010 )
b1010 -
#390
0#
#395
1#
#400
0#
b1011 (
#405
b110 !
b110 ,
b1011 +
b1011 .
1#
b1011 $
b1011 )
b1011 -
#410
0#
#415
1#
#420
0#
b1100 (
#425
b1000 !
b1000 ,
b1100 +
b1100 .
1#
b1100 $
b1100 )
b1100 -
#430
0#
#435
1#
#440
0#
b1101 (
#445
b1010 !
b1010 ,
b1101 +
b1101 .
1#
b1101 $
b1101 )
b1101 -
#450
0#
#455
1#
#460
0#
b1110 (
#465
b1100 !
b1100 ,
b1110 +
b1110 .
1#
b1110 $
b1110 )
b1110 -
#470
0#
#475
1#
#480
0#
b1111 (
#485
b1110 !
b1110 ,
b1111 +
b1111 .
1#
b1111 $
b1111 )
b1111 -
#490
0#
#495
1#
#500
0#
b10000 (
#505
1#
#510
0#
b0 $
b0 )
b0 -
#515
0"
b0 !
b0 ,
b0 +
b0 .
1#
#520
0#
b0 (
1'
b1 *
0&
#525
1#
#530
0#
#535
1#
#540
0#
b1 (
#545
b1 +
b1 .
1#
b1 $
b1 )
b1 -
#550
0#
#555
1#
#560
0#
b10 (
#565
b1 !
b1 ,
b10 +
b10 .
1#
b10 $
b10 )
b10 -
#570
0#
#575
1#
#580
0#
b11 (
#585
b11 +
b11 .
1#
b11 $
b11 )
b11 -
#590
0#
#595
1#
#600
0#
b100 (
#605
b10 !
b10 ,
b100 +
b100 .
1#
b100 $
b100 )
b100 -
#610
0#
#615
1#
#620
0#
b101 (
#625
b101 +
b101 .
1#
b101 $
b101 )
b101 -
#630
0#
#635
1#
#640
0#
b110 (
#645
b11 !
b11 ,
b110 +
b110 .
1#
b110 $
b110 )
b110 -
#650
0#
#655
1#
#660
0#
b111 (
#665
b111 +
b111 .
1#
b111 $
b111 )
b111 -
#670
0#
#675
1#
#680
0#
b1000 (
#685
b100 !
b100 ,
b1000 +
b1000 .
1#
b1000 $
b1000 )
b1000 -
#690
0#
#695
1#
#700
0#
b1001 (
#705
b1001 +
b1001 .
1#
b1001 $
b1001 )
b1001 -
#710
0#
#715
1#
#720
0#
b1010 (
#725
b101 !
b101 ,
b1010 +
b1010 .
1#
b1010 $
b1010 )
b1010 -
#730
0#
#735
1#
#740
0#
b1011 (
#745
b1011 +
b1011 .
1#
b1011 $
b1011 )
b1011 -
#750
0#
#755
1#
#760
0#
b1100 (
#765
b110 !
b110 ,
b1100 +
b1100 .
1#
b1100 $
b1100 )
b1100 -
#770
0#
#775
1#
#780
0#
b1101 (
#785
b1101 +
b1101 .
1#
b1101 $
b1101 )
b1101 -
#790
0#
#795
1#
#800
0#
b1110 (
#805
b111 !
b111 ,
b1110 +
b1110 .
1#
b1110 $
b1110 )
b1110 -
#810
0#
#815
1#
#820
0#
b1111 (
#825
b1111 +
b1111 .
1#
b1111 $
b1111 )
b1111 -
#830
0#
#835
1#
#840
0#
b10000 (
